[{"id":"2aa79b730f88","collection":"sites_ja","data":{"slug":"2aa79b730f88","title":"Sweetie Fox","lang":"ja","date":"2025-10-29T00:00:00.000Z","description":"Sweetie Foxは、大人のエンターテイメントの新星です。彼女は彼女の魅惑的な魅力と彼女の魅力的なロールプレイングに魅力的です","canonical":"https://theporndude.com/zh/11666/sweetiefox","affiliate_url":"https://fansly.com/r/missavdh?redirect=SweetieFox","rating":4,"siteOrder":1,"price":"free","tags":[],"features":[],"categories":[{"id":"best-fansly-girls-list-reviews","collection":"categories_ja"}],"screenshot_url":"https://cdn.staticstack.net/assets/img/r-thumbs/aaed4_sweetiefox_small.jpg","image_alt":"スウィーティーフォックス、ベストファンリーガールズリスト","scraped_at":"2025-10-29T13:42:48.513Z","iconSpritesheet":"custom-favicon-spritesheet.png","iconPosition":"-64px -576px","iconClassName":"ctm-icon11666","logoIconClass":"icon11666","pros":["ゴージャスな顔、くびれたおっぱい、完璧なお尻","現実のワイフ。"],"cons":["彼女が他のクリエイターともっとコラボレーションするのを見たい。"],"detailedDescription":"<p>Sweetie FoxのAV！スウィーティー・フォックスはアダルト業界で最もホットなセンセーションの一人で、魅惑的なパフォーマンスでスクリーンを燃え上がらせている。生の才能と魅惑的な魅力で一躍脚光を浴び、ファンからもパフォーマー仲間からも人気を集めている。</p><p></p><p>2001年7月21日、ロシアのエカテリンブルク生まれのスウィーティーは、観客を魅了しっぱなしにする術を心得ている、熱く魅惑的なパフォーマーだ。彼女は真の快楽の達人であり、彼女のエロティックな逃避行の記憶は、見終わった後もずっと心に残るだろう。</p><p></p><p>スウィーティーのむせ返るようなまなざしは、あなたの魂を裸にし、彼女の媚びない微笑みは、どんなに冷たい心さえも溶かしてしまうだろう。スレンダーなウエストから長く引き締まった脚線美は圧巻で、何時間もの快楽と探求を約束する。揺れるたびに、弾むたびに、魅惑的なディスプレイがあなたを魅了し、そのしなやかな頬をつかみたいと切望させる。</p><p></p><p>スウィーティーがアダルト業界のランキングで急上昇した大きな要因のひとつは、彼女の泡のような人柄と、観客を夢中にさせる能力にある。この仙女のエッチな姿を一度でも見たら、一生虜になってしまう。</p><p></p><p>スウィーティー・フォックスは、才能あるアダルト・パフォーマーであるだけでなく、クリエイティブで情熱的なコスプレイヤーでもある。魅惑的なアダルト・コンテンツに加え、彼女は魅惑的なコスプレでお気に入りの架空のキャラクターに命を吹き込み、ファンを喜ばせている。細部へのこだわりと芝居のセンスで、スウィーティーはビデオゲーム、映画、アニメなどの愛すべきキャラクターの数々に変身する。</p><p></p><p>彼女のコスプレコンテンツは、ひとつひとつのコスチュームを丹念に作り上げ、彼女が扮するキャラクターの個性に没頭することで、視覚的な楽しみを与えてくれる。セクシーで魅惑的なものから、キュートでおちゃめなものまで、スウィーティーはそれぞれのキャラクターの本質を体現するために難なく適応し、彼女のコスプレパフォーマンスをより魅力的なものにしている。</p><p></p><p>彼女の魅惑的な美しさ、観客を魅了する能力、そして一流のコスプレ衣装のおかげで、スウィーティーは瞬く間に数百万ビューを獲得した。多くのムラムラしたフェラチオ好きが、自分の好きなアニメキャラがファックされるのを見たくてうずうずしていた。そして、美しいスウィーティーがエルヴのコスプレをしてファックされるシーンに登場すると、このムラムラしたおバカさんたちは狂喜乱舞した。スウィーティーがコスプレをしながら喘ぐ姿を見るだけでは満足できなかったのだ。</p><p></p><p></p><h3>完璧なフェラチオ</h3><p></p><p></p><p>スウィーティー・フォックスがひざまずくと、お楽しみが待っていることがわかる。彼女の熱意と熱心さは、太いチンコをじっくりと味わい、悦ばせる動きのひとつひとつに表れている。熟練した舌の動きと甘美な唇の優しい愛撫で、彼女はパートナーに歓喜の呻き声を上げさせ、観客を魅了する体験を作り出す。</p><p></p><p>スウィーティーの丸いお尻は、崇拝されることを懇願するが、彼女の完璧なお尻のもっと興味深い点は、それができることである。彼女のお尻は、太いチンコを楽しませ、精液を搾り取るようにできている。スウィーティーがチンポに乗るのを見たことがないのなら、人生最高のエンターテイメントのひとつをまだ目撃していないことになる。</p><p></p><p>スウィーティーのチンコ乗りの実力については、まだ説明するまでもないだろう。彼女は野生の種馬のようにチンコを乗りこなし、観客を恍惚の旅へと誘う。彼女の腰は、魅惑的な流動性で揺れ、グラインドし、パートナーの興奮のリズムと完璧に同期する。スウィーティーは、いつペースを上げれば恋人を欲望で狂わせ、いつペースを落とせば二人の親密なつながりのうっとりするような一瞬一瞬を味わえるかを知っている。</p><p></p><p>このロシア美女は、難なくディックにまたがることができる。彼女が硬いシャフトにまたがると、即座にマジックが起こり、彼女が主導権を握り、パートナーを電撃的な快楽の旅へと導く。彼女の腰は魅惑的な優美さで動き、揺れ、グラインドし、抗いがたいリズムを作り上げ、彼女もパートナーも興奮に狂う。</p><p></p><p>Sweetieの独占コンテンツが欲しい人は、Manyvidsで彼女のビデオを購入するか、OnlyFansのページを購読してほしい。彼女のOnlyFansアカウントは、ザーメン排出コンテンツのフリーキングストアハウスだ。そこでは、彼女のセクシーなランジェリーの画像を見ることができる。また、この貪欲な淫乱女が尻を犯されている動画も見つかるだろう。</p><p></p><p>遊び心のあるからかいから奔放なパフォーマンスまで、彼女は購読者の野生の欲望を満たすために手段を選ばない。</p><p></p><p>このエッチな美女のOnlyFansページを購読するもう一つの特典は、購読者として彼女と1対1で交流できることだ。そう、スウィーティーは購読者のスケベな妄想をくすぐるようなエッチな会話をするのが好きなのだ。彼女とのチャットは、弛緩した幸せな乳首で終わるかもしれない。ただし、このエッチなセダクティブとチャットするためには、2、3ドルを支払う必要がある。</p><p></p><p></p><h3>ポルノ以外の人生</h3><p></p><p></p><p>彼女の絵を何枚か見たことがあるが、才能あるアーティストであることは認めざるを得ない。もし彼女がAVの道を選ばなければ、プロの芸術家になっていたに違いない。</p><p></p><p>スウィーティーがカメラの前で豆をはじく以外に好きなことのひとつは旅行だ。このロシア人モデルは、新しい目的地を訪れ、新しい文化を体験するスリルを楽しんでいる。</p><p></p><p>このモデルはまた、定期的にジムに通い、スモーキング・ホット・ボディを維持している。スウィーティの完璧な曲線美と引き締まったスラリとした脚は、ジムでの数え切れないほどの熱心なトレーニングの賜物だ。</p><p></p><p>彼女は、その魅力的な体格が最大の財産であることを自覚し、自信と誇りを持ってそれを受け入れている。スウィーティー・フォックスは、自分の体を完璧に鍛える方法を心得ており、ファンをその魅惑的な魅力に畏敬の念を抱かせている。</p><p></p><p>スウィーティー・フォックスの生活を覗いてみたいなら、彼女のソーシャルメディア・ページをフォローしてみよう。このスマット・スターレットは、ツイッターとインスタグラムで活発に活動しており、彼女自身のセクシーな画像をアップロードし、ファンたちと交流している。彼女のインスタグラム・ページには、セクシーなランジェリーを身にまとい、甘美な曲線美を見せつけるスチーム画像が満載だ。</p><p></p><p>スウィーティーのツイッター・ページはまさに金鉱だ。何も着ていない彼女の画像や動画が山ほどある。美しい変態たちは、彼女のくびれたおっぱいと完璧なお尻に目を奪われることだろう。また、このモデルは定期的に新鮮なコンテンツの断片をアップロードしている。そのスニペットはホットで、彼女のアクション（硬いチンコを扱う）を見てウズウズするだけだろう。</p><p></p><p>あなたが女性に性的魅力を感じないのでなければ、彼女のツイッター・ページを見るたびに猛烈に勃起してしまうだろう。彼女のツイッターにアクセスする前に、ローションとティッシュを用意し、勃起の痛みをすぐに和らげられるようにしておこう。</p><p></p><p></p><h3>結論</h3><p></p>"}},{"id":"eb12c24f22a5","collection":"sites_ja","data":{"slug":"eb12c24f22a5","title":"Angela White","lang":"ja","date":"2025-10-29T00:00:00.000Z","description":"アンジェラホワイトは、オーストラリアの世界トップポルノスターの1人であり、数多くの成人産業賞を受賞しています。このガイドでは、彼女が今まで見たことのないスタイルを紹介します。","canonical":"https://theporndude.com/zh/11730/angelawhite","affiliate_url":"https://fansly.com/r/missavdh?redirect=ANGELAWHITE","rating":5,"siteOrder":2,"price":"free","tags":[],"features":[],"categories":[{"id":"best-fansly-girls-list-reviews","collection":"categories_ja"}],"screenshot_url":"https://cdn.staticstack.net/assets/img/r-thumbs/8d633_angelawhite_small.jpg","image_alt":"アンジェラ・ホワイト、ベストファンリーガールズリスト","scraped_at":"2025-10-29T13:42:58.907Z","iconSpritesheet":"custom-favicon-spritesheet.png","iconPosition":"-256px -576px","iconClassName":"ctm-icon11730","logoIconClass":"icon11730","pros":["顔を見ずとも、ほとんどの人がすぐにわかるエリート級の巨乳","性格が悪く、ポルノに対する純粋な愛情がどのシーンにも表れている","アンジェラは、グーニングポルノのサブカルチャーを最初に認識したポルノスターの一人","フェラチオからフェムドムまで、非常に幅広いジャンルのポルノに出演している。"],"cons":["アンジェラ・ホワイトのシーンは当たり外れがあるが、自動的に過大評価される。"],"detailedDescription":"<p>ごきげんよう！AV界の大スターに会うため、オーストラリアに向かう。オーストラリアは過去にいろいろなことで知られてきた。キュートなコアラやフレンドリーな地元の人々のようなクールなものもあれば、ホホジロザメの襲撃や悪名高いマーク''チョッパー''リードのようなキュートではないものもある。</p><p></p><p>ありがたいことに、今日の有名なオーストラリア人のレビューは、前述のチョッパーの話ではない。そう、私たちが知っているエリート級のフェラチオ女、アンジェラ・ホワイトだ！</p><p></p><p>アンジェラ・ホワイトは、顔を見なくてもおっぱいだけでわかるタイプのポルノスターだ。この誇り高きニンフォマニアックは、赤道直下でも指折りの乳腺を授かっただけでなく、業界屈指の大物ポルノ女優たちと共演したこともある情熱的なヤリマンでもある。</p><p></p><p>しかし、彼女のおっぱいには詳しいかもしれないが、このポルノのアイコンのことを本当によく知っているだろうか？今日は、このゴージャスな淫乱女のパンティの下に潜り込み、彼女の謙虚な始まりから、最も見逃せないポルノ・パフォーマンス、目を見張るような事実、そして彼女が最近何をしているのかまで、彼女について知るべきことをすべて見つけ出そう。</p><p></p><p>象徴的なクロコダイル・ダンディーの言葉を借りれば、\"それはアバズレじゃない。これはアバズレだ！』。ムラムラした読者諸君、オーストラリアが誇る娼婦であり、アダルト業界の象徴である彼女を間近で見る時が来た。さあ、心の準備を！</p><p></p><p></p><h3>アンジェラ・ホワイトとは？</h3><p></p><p></p><p>18歳になるやいなや、ヌードモデルの世界に飛び込んだアンジェラ・ホワイトは、大学での勉強と両立させながら、2010年にジェンダー研究の首席で卒業した。後ろで笑ってないで！</p><p></p><p>2011年春、アンジェラはヌードモデルからアップグレードし、『Score』で初めてのフェラチオ・ハードコア・シーンを披露した。この巨乳娼婦がアダルト・スタジオで数々の重要な演技を披露するのに時間はかからず、2013年、彼女は公式ウェブサイトAngelaWhite.comを公開した。</p><p></p><p>アンジェラはすぐに、ほとんどのポルノ女優志望者が夢見るようなポルノキャリアを築き始めた。彼女は108以上のアダルト賞と170以上のノミネートを受賞し、AVNとXRCOの殿堂入りを果たした。特に、AVN年間最優秀女性パフォーマー賞を女性として初めて3度受賞した。</p><p></p><p>彼女はまた、誇り高きFleshlightガールでもあり、Brazzersのプロデューサーであるライアン・ホーガンからは「この業界におけるプロフェッショナリズムとスターダムの絶対的頂点」と評されている。彼女をもっと見たい？そうでしょう！さあ、このチンポに飢えたアバズレのパンティーを引き裂いて、彼女がポルノ界に何をもたらすのか見てみよう！</p><p></p><p></p><h3>アンジェラ・ホワイトの必見AVシーン</h3><p></p><p>● アンジェラが反ポルノプロパガンダに洗脳された社会を解放し、唾液まみれのフェラで全員をポルノ好きのグーナーに変えてしまうという、忘れがたい未来のディストピア世界を舞台にしている。</p><p>アンジェラ・ホワイト＆オータム・フォールズと潮吹きオーガズム - このシーンでは、アンジェラ・ホワイトのポルノへの情熱が発揮され、彼女はオータム・フォールズを潮吹きオーガズムのウサギの穴に突き落とす。この少女は人間ホースと化しており、潮が噴出するたびにアンジェラが見せる変態的な喜びの表情がたまらない。このポルノスターの両巨乳を覆う大量のベビーオイルも相まって、まさに見逃せない壮大なアンジェラ・ホワイトのポルノが完成した！</p><p>● アンジェラ・ホワイトのフェムドム - 全体的にフレンドリーな印象のアンジェラ・ホワイトだが、この女性支配ポルノでは不吉な一面を剥き出しにしている。赤いラテックスのランジェリーで身を包んだ彼女の従順な男たちは、アンジェラが彼の顎に精液を浴びせ、檻に閉じ込める前に、クィーニングチェアの上で彼女の穴に舌を入れられ、試される。哀れな野郎は、彼女の象徴的なおっぱいを試すことすらできなかったが、少なくとも彼は、彼女のマンコとケツの穴を地球最後の食事のように食べた。</p><p>● アンジェラ・ホワイトのダークサイド - アンジェラがジュールズ・ジョーダンのために撮ったこのゴージャスな輪姦シーンは実にワイルドで、彼女が黒と白のチンコのビュッフェを全穴に受けるのを見た。ダブル挿入、ハードなアナル、華麗なディープスロート・アクションが、オーガズムに満ちた眼差しとぽっかりと空いた穴と相まって、彼女の最もハードコアな演技のひとつとなっており、彼女は象徴的な笑顔でそのすべてを受け止めている。多くの人は、この変態ポルノ・ケーキのアイシングは、彼女の黒革の肘手袋とラテックスの腿高ブーツだと思っている。しかし、本当のアイシングは、彼女が最後に受けるみだらなぶっかけセッションだ。何時間もチンコをしゃぶり続けた彼女の赤らんだ目にザーメンが降り注ぐ様は壮絶だ！</p><p></p><p></p><h3>アンジェラ・ホワイトの興味深い事実</h3><p></p><p></p><p>まず、アンジェラ・ホワイトが出演したポルノシーンは、目を見張る900シーンにも及び、あるシーンで盲腸が破裂して病院に運ばれた、とポルノスターのキーラン・ホワイトが主張しているほどだ。そのため、アンジェラ・ホワイトに体を休めるよう懇願するファンもいるが、アンジェラ・ホワイトは「好きな仕事をするなら、一生一日も働くことはない」と答えている。</p><p></p><p>多くの人が知らないことのひとつに、アンジェラ・ホワイトは代表的なポルノ女優であると同時に、ロサンゼルスを拠点とするAGWエンターテインメントという自身のアダルト・プロダクションも持っているということがある。</p><p></p><p>アンジェラ・ホワイトは政治活動にも積極的で、2010年のオーストラリア・ビクトリア州の選挙では、地元のセックスワーカーの権利を守ることを掲げて政治家候補として立候補した。ワル！</p><p></p><p>アンジェラ・ホワイトは、ガールフレンド・フィルムズと配給契約を結んだ直後の2014年末に、象徴的なFleshlightブランドのために彼女のアソコの型を作らせた。興味深いことに、彼女はFleshlightのモデルになった史上初のオーストラリア人であり、ネッド・ケリーやケイト・ブランシェットらと並んでオーストラリアの歴史に名を刻んだ。しかし、残念なことに、この記事を書いている時点では、後者2人は公式のFleshlightを持っていない。</p><p></p><p>アンジェラ・ホワイトが大量のAVN賞を受賞していることは周知の事実だが、彼女が2018年にラスベガスで開催された第35回AVN賞のイベントで、アリエス・スピアーズとハーリー・ロッツとともにステージに立ち、共同司会者まで務めたという事実を多くの人が見逃している。</p><p></p><p></p><h3>彼女のポルノ・タレント・トップ3とは？</h3><p></p><p></p><p>● おっぱいオナニー......当たり前でしょ？アンジェラ・ホワイトに授けられたその巨大で天然の乳腺は、男性の玉袋を空にするために作られたもので、彼女の乳首責めのスキルはこの世のものとは思えない。アンジェラ・ホワイトがシースルーの黒いトップスを着て、幸運な男のペニスを中に閉じ込め、彼が透け透けの素材越しにザーメンをぶちまける前に、世紀のローションまみれの乳首責めをするシーンだ。幸運なことに、彼女はふしだらな秘書用メガネをかけているので、流れ出たジズが目に入ることはない！</p><p>● アンジェラ・ホワイトの灼熱の瞳は、あなたのムラムラした魂に深く焼き付く。そして彼女は、セックス、BJ、おっぱい責めの間、その瞳を最大限に使い、ファックしている男たちの玉から最後の一滴まで種を搾り取る。</p><p>● アナルファック-アンジェラはアナルが大得意で、尻の穴にペニスをぶち込まれただけで、オーガズムのウサギの穴に落とされるような絶頂を味わうことができる。さらに、彼女のムラムラした表情は、尻を犯されているときが最高であることが多い！</p><p></p><p></p><h3>アンジェラ・ホワイトは今どこで何をしているのか？</h3><p></p><p></p><p>彼女の公式Twitterアカウントによると、アンジェラは世界最大のポルノキャピタルのひとつ、ロサンゼルスを拠点にしている。大手スタジオでハードコア・ポルノを作るだけでなく、OnlyFansのアカウントも持ち、ライブ・セックス・カム・サイトに出演することもある。</p><p></p><p>しかしもちろん、完璧なポルノスターなどいない。そこで、アンジェラ・ホワイトの究極ガイドの締めくくりとして、彼女のポルノパーソナリティの長所と短所を見てみよう。</p>"}},{"id":"88371ab8352b","collection":"sites_ja","data":{"slug":"88371ab8352b","title":"Amouranth","lang":"ja","date":"2025-10-29T00:00:00.000Z","description":"Amouranthは、最も有名で成功したTwitchストリーマーの1人です。","canonical":"https://theporndude.com/zh/11783/amouranth","affiliate_url":"https://fansly.com/r/missavdh?redirect=Amouranth","rating":5,"siteOrder":3,"price":"free","tags":[],"features":["游戏"],"categories":[{"id":"best-fansly-girls-list-reviews","collection":"categories_ja"}],"screenshot_url":"https://cdn.staticstack.net/assets/img/r-thumbs/fa8b7_amouranth_small.jpg","image_alt":"Amouranth、最高のファンリーガールズリスト","scraped_at":"2025-10-29T13:43:09.060Z","iconSpritesheet":"custom-favicon-spritesheet.png","iconPosition":"-416px -576px","iconClassName":"ctm-icon11783","logoIconClass":"icon11783","pros":["常にセクシーなライブストリーム","いくつかの適切なハードコア動画","スマット用に作られたゴージャスなボディ","魅力的な性格"],"cons":["twitchでスマット"],"detailedDescription":"<p>アムランスのAV！もうお分かりですね。あなたはAmouranthを知っている。誰もがAmouranthを知っている。彼女はTwitchに革命を起こした。Twitchが無料ゲーム配信サービスからオナニー配信サービスになったのも彼女のおかげだろう。私は嬉しくない。ポルノサイトはすでに100万もあるし、そのほとんどはすでにここに掲載されている。ポルノ以外の空間にオ○ニーを持ち込む必要はない。Twitchは子供たちに大人気だ。このプラットフォームがオ○ニーを気軽に受け入れているのが気に入らない。彼らはこのクソを抑制しようとしているが、彼らのルールは裏目に出続けている。水の中でなければビキニでストリームできないようにした。彼女たちがよりセクシーになる手助けをしているようなものだ。</p><p></p><p>私はビッチが濡れてワイルドになることに文句を言う最後の人間だ。私はそれが大好きだ。毎日ファックしてるよ。以前もアムランスでファックしたし、今回もするさ。彼女はいいものを持っている。問題は、彼女がいるプラットフォームは......子供に優しいはずなんだ。考えすぎはよくない。結局のところ、僕はこの子のおっぱいとお尻を評価するためにここにいるんだ。僕の読者はみんなアダルトだし、ここはアダルトサイトなんだから、本来、僕がこの女をファップ素材として取り上げることに何の問題もない。彼女は、自分がまさにそう宣伝していることを知っている。彼女がそれを認めているのを聞いたことがある。</p><p></p><p></p><h3>コスプレ女王</h3><p></p><p></p><p>つまり、彼女は魅力的だった。彼女は本当にコスチュームとこのクソ仕事を愛しているのがわかった。彼女はファンタスティックな生き物の生き写しになろうとした。ジェシカ・ニグリは彼女の前にも同じようなことをやっていた。それでも、2人ともおっぱいで知られている。</p><p></p><p></p><h3>彼女はたまらなく売れている</h3><p></p><p></p><p>そうだね、認めよう。Amouranthの外向的で魅力的な性格は、彼女のコミュニティを維持する上で大きな役割を果たした。そう、彼女は歩くセックス・ドールなのだ。しかし、彼女のストリームやソーシャルメディアへの投稿には、独特のカリスマ性が光っている。彼女は明らかに無数のファンの心を捉えている。彼女は自分が何をしているのかよくわかっているし、楽しんでいる。彼女は、ファンがパンツに片手を突っ込んだ状態で彼女のコンテンツを見ていることを気にしていない。彼女は基本的にそれを奨励しているのだ。</p><p></p><p></p><h3>Twitchをファップゾーンに変える</h3><p></p><p></p><p>そして、ホットタブのメタがあった。Amouranthはホットタブ・メタの女王だった。知らない人のために説明すると、ホットタブ・ストリームとは、ストリーマーが何も身につけず、ホットタブやプールの中で視聴者と気軽におしゃべりすることだ。当然ながら、これは物議を醸した。つまり、子供たちがこのクソを見たのだ。しかし、Twitchは昼間の安全なストリーム配信の場であって、スマット配信の場ではない。でも、Amouranthはおっぱいでそれを解決してくれた。</p><p></p><p></p><h3>ストリップする権利のために戦う</h3><p></p><p></p><p>Amouranthは、この論争をあまり気にしていないようだ。彼女は、ファンは彼女が裸になり、激しくするのを見に来たのだと知っていたからだ。彼女はインターネットが彼女に投げつけたものすべてを乗り越えてきた。彼女はストリーミング・アワードを受賞しているのだ。</p><p></p><p></p><h3>もちろん、彼女にはOnlyFansがいる。</h3><p></p><p></p><p>Amouranthのような多くのエッチなストリーマーは、ソフトコアからハードコアへの道を、何年にもわたる長いマーケティング・キャンペーンとともに歩んできた。ベル・デルフィーヌも同じことをした。最近、彼女はカメラでアナルファックされているが、数年前、私たちは彼女の乳首が何色なのかを知るために身を屈めた。長期的なマーケティングによるからかいだ。</p><p></p><p></p><h3>ホットな赤毛がインターネットを支配する</h3><p></p><p></p><p>彼女のアソコを見るべきね。ブランチみたいだよ。彼女の股間に顔を埋めて、しばらくそこで暮らしたい。彼女もそれをわかっている。ビデオでの彼女のキャッキャウフフぶりを見ればわかる。私たちは彼女を消費していると思っているけれど、本当は彼女は私たちを小銭稼ぎに利用している。たくさんのオーガズムと精液を伴う、とても素敵な共生関係だ。</p><p></p><p></p><h3>ホットで、ムラムラしていて、金儲けの天才。</h3><p></p><p></p><p>彼女のOnlyFansは、天才的な起業家精神を証明している。複数の階層、さまざまな形のコンテンツ、インタラクション、ボーナス、景品、その他神のみぞ知るものがある。彼女はできる限りの方法でファンから金を搾り取り、長期戦を演じている。この時点で、この女はクソ金持ちに違いない。彼女のネット上での活動はすべて、事前に入念に計画されていることがわかる。彼女のおっぱいとお尻の後ろには巨大なチームがいて、お金が入り続けるようにしているのだろう。</p><p></p><p></p><h3>彼女はパトロンを持っている</h3><p></p><p></p><p>じゃあ、パトロンには何があるの？高解像度の写真セット。独占ビデオや舞台裏のコンテンツ。個人的な交流の可能性など、セクシーなコンテンツが盛りだくさん。上位層には、1対1のチャットなどの特典があります。Amouranthと1対1で話したいと思わない人はいないよね？この際、アソコを貸し出せばいいのに。パトロンになるごとに、アムーランスの新たな魅力が引き出されていく。</p><p></p><p></p><h3>マッドリスペクト</h3><p></p><p></p><p>反発を受けようが、賞賛を浴びようが、彼女は親しみやすい。最近、彼女がインタビューに答えているのを見たが、ファンについて質問され、彼女は、ファンがファップするためにやっていることは知っているが、気にしないし、気にしない、とジョークを飛ばしていた。いいじゃない。彼女はそれが好きなんだ。彼女は悪いことをされているとは感じていない。<strong>彼女はネット上では大きな存在感を示しているが、その裏では金とネット上の名声を夢見るただのセクシーな赤毛</strong>なのだ。</p>"}},{"id":"1e16db55b39e","collection":"sites_ja","data":{"slug":"1e16db55b39e","title":"Morgpie","lang":"ja","date":"2025-10-29T00:00:00.000Z","description":"モルピーは、成人業界で最高のアーティストの一人です。彼女の完璧なフィギュアとプロのディックハンドリングスキルは、彼女に忠実なファン層を獲得しました。","canonical":"https://theporndude.com/zh/11687/morgpie","affiliate_url":"https://fansly.com/r/missavdh?redirect=morgpie","rating":4,"siteOrder":4,"price":"free","tags":[],"features":[],"categories":[{"id":"best-fansly-girls-list-reviews","collection":"categories_ja"}],"screenshot_url":"https://cdn.staticstack.net/assets/img/r-thumbs/d044c_morgpie_small.jpg","image_alt":"Morgpie、ベストファンリーガールズリスト","scraped_at":"2025-10-29T13:43:20.366Z","iconSpritesheet":"custom-favicon-spritesheet.png","iconPosition":"-144px -576px","iconClassName":"ctm-icon11687","logoIconClass":"icon11687","pros":["ゴージャスな顔、ナイスなおっぱい、そして崇拝に値する丸くて柔らかいお尻","野生の種馬のようにチンコを乗りこなす","視聴者をスクリーンに釘付けにする魅力的な性格。"],"cons":["他のアダルト・パフォーマーとのコラボレーションはない。"],"detailedDescription":"<p>MorgpieのAV！2000年6月1日生まれのモルグピーは、アダルト業界屈指の才能の持ち主。彼女はソーシャルメディアの有名人であり、ストリーマーであり、プロのフェラチオ師でもある。彼女のフェラを見たことがない人は、人生で最もエキサイティングな光景のひとつを期待して損をしている。</p><p></p><p>Morgpieは、ファンを畏敬の念を抱かせる羨望の体型の絶対的なスタナーだ。彼女の曲線美のボディは、丸くて柔らかいお尻が自慢で、たまらない。動いていても、カメラに向かってポーズをとっていても、彼女のお尻は注目を集め、心を躍らせる。そして、彼女の胸に関して言えば、その魅力は否定できない。モーグのおっぱいはふくよかでペロペロしており、彼女の官能的な魅力を完璧に引き立てている。</p><p></p><p>モルグパイがポルノ業界のランキングで瞬く間にトップに躍り出た理由を理解するのは難しくない。これほど魅惑的な体格を持つ彼女が、スクリーンの内外で彼女のアクションを目撃することを熱望する熱狂的なファンを獲得したのも不思議ではない。</p><p></p><p>肉体的な特徴に加え、モーグピーのスクリーン上での存在感も同様に魅惑的だ。彼女のカリスマ性と情熱はすべてのシーンで輝き、観客に忘れがたい印象を残す。彼女の演技は、誘惑と本物らしさが見事に融合しており、視聴者はスクリーンの中で彼女が繰り広げるファンタジーにどっぷりと浸ることができる。</p><p></p><p>彼女のビデオを見ていると、あからさまにわかるのは、彼女がフェラチオ、特に太くて硬いフェラチオが大好きだということだ。彼女を見続けていると、この可愛い女性が無邪気なのではなく、ディープスロート・クイーンであることがわかる。彼女の熟練した舌の動きと甘美な唇の優しい愛撫は、硬いチンコを弛緩させるように計算されている。</p><p></p><p>この美しい淫乱女は、チンコを乗りこなすエキスパートでもある。彼女がチンコの上に座ると、豊満な腰がグルグルと回転する様は魔法の一言に尽きる。一日中見ていても、翌日同じことをするために目覚めても、まだ飽きない光景だ。この巨乳モデルは、勃起したチンコの上に乗って、チンコが持っている精液を出し尽くして弛緩するまで、跳ねるのを止めない。</p><p></p><p>モルグピーはマンコを悦ばせるプロでもあり、それが彼女の甘いツインテであろうと、セックス・ドールの堅い穴であろうと、彼女は視聴者を息も絶え絶えにさせてやまない。この美女が勃起したチンコに窒息するのを見るのと同じくらい興奮するのは、彼女が太いディルドでタイトでジューシーなマンコを満たすのを見ることだ。モルグピーはいつも時間をかけて快楽を味わう。太いディルドで穴を開ける前に、快楽ポイントを官能的に愛撫することから始める。</p><p></p><p>彼女の独占的なザーメン排出コンテンツを手に入れたい人は、彼女のOnlyFansとFanslyのページにアクセスしてほしい。彼女のOnlyFansは宝の山だ。そこで見つかる宝物は、ヲタクの心を歓喜で弾ませるタイプのものだ。私が言っているのは、猛烈な勃起を誘発するようなコンテンツのことだ。</p><p></p><p>モルグピーのOnlyFansページを購読すると、楽しめるのは肉体を興奮させるコンテンツだけではない。モルグパイと1対1で交流する機会もあるのだ。OnlyFansは、クリエイターと購読者がシームレスに彼女と交流できるエコシステムを提供することを目指している。</p><p></p><p>OnlyFansのページにアクセスする前に警告しておくが、Morgpieとのチャットは無料ではない。彼女のOnlyFansページにアクセスするには、まず購読料を支払わなければならない。購読することで、エッチなモデルとのメッセージ交換は保証されますが、彼女の注意を引くのは全く別のゲームです。</p><p></p><p>Morgpieは、すべての購読者に注意を払おうと最善を尽くしているが、すべての購読者と連絡を取り続けるのは大変な作業だ。それゆえ、このモデルは、彼女を喜ばせるためにわざわざ来てくれるファンにほとんどの注意を向けることにしている。これらのファッカーは、彼女にプレゼントを浴びせたり、彼女の要求を満たすことを楽しんでいる。もし、あなたがモデルの注意を引きたいのなら、あなたも同じことをしなければならない。</p><p></p><p>モルグピーは間違いなく、近年のポルノ業界から現れた最高のエンターテイナーだ。チンコとジューシーなマンコを喜ばせる彼女の才能は否定できない。モルグパイが他のコンテンツ出演者とコラボしないのは残念だ。</p><p></p><p>この長身の女狐が、黒人の巨根によってマンコを引き伸ばされ、精液で満たされるところを見たいものだ。彼女が一度に複数の太いチンコですべての穴を満たされるのを見たらもっと興奮するだろう。残念ながら、モルグピーはパートナーとのコンテンツ作りを好むので、すぐには実現しないと思う。</p><p></p><p></p><h3>ポルノ以外の生活</h3><p></p><p></p><p>モーギーは大のアニメファンで、日本のアニメのエキサイティングな世界に没頭するのが大好きだ。彼女はナルトのタトゥーを2つも入れている。このモデルはホラー映画の大ファンでもある。</p><p></p><p>この超ホットなストリーマーについて知りたい人は、彼女の様々なソーシャルメディアページをフォローしてみよう。MorgpieはTwitter、Instagram、Reddit、TikTok、Twitchで活動している。彼女のツイッターとインスタグラムのページには、ほとんど想像を絶するようなスケスケの服を着た彼女の画像や動画があふれている。</p><p>このエッチなストリーマーのツイッターページをチェックするたびに、オトナたちは勃起してしまうことだろう。</p><p></p><p>モーグピーのRedditページをチェックするのは控えよう。彼女のRedditアカウントには、画像、クリップ、Gifが山ほどあり、死んだ神父でさえ勃起してしまうだろう。さらに、彼女はこうも言っている。</p><p></p><p>このゴージャスなポルノスターはYouTubeチャンネルも持っており、楽しいコンテンツが満載だ。私は一日の大半を彼女のチャンネルのビデオを見て過ごした。最も興味深いジャンルのコンテンツは、彼女のセックスグッズのレビューだった。見ていて面白いだけでなく、ためになる。彼女は、あなたが特定のセックスグッズを購入したときに楽しめることをすべて教えてくれる。この美しいモデルは、彼女がレビューしているセックス・ドールがどんなものであれ、そのペロペロのおっぱいからジューシーな穴まで、視聴者に確実に伝えるために手を抜かない。</p><p></p><p></p><h3>結論</h3><p></p><p></p><p>このヒナのコンテンツは、片付けなければならない仕事がたくさんある人は見ないほうがいい。ひとたび彼女が画面に現れたら、もう満足できないだろう。お前らフェラ好きは、手首が切れるまで、自分の小さな乳首を撫で回すことになるだろう。</p>"}},{"id":"425bfd6e96a8","collection":"sites_ja","data":{"slug":"425bfd6e96a8","title":"Brandi Love","lang":"ja","date":"2025-10-29T00:00:00.000Z","description":"ブランディラブは、ポルノ業界で最も象徴的な熟女クーガーの1つです。そして、成人財業界のベテラン。彼女の政治的経験から彼女の最もワイルドなポルノの才能まで、ブランディ・ラブのプロフィールはあなたに彼女のすべての輝かしい物語を明らかにします。","canonical":"https://theporndude.com/zh/11731/brandilove","affiliate_url":"https://fansly.com/r/missavdh?redirect=brandilove","rating":5,"siteOrder":5,"price":"free","tags":[],"features":[],"categories":[{"id":"best-fansly-girls-list-reviews","collection":"categories_ja"}],"screenshot_url":"https://cdn.staticstack.net/assets/img/r-thumbs/3ed98_brandilove_small.jpg","image_alt":"Brandi Love、最高のファンリーガールズリスト","scraped_at":"2025-10-29T13:43:32.269Z","iconSpritesheet":"custom-favicon-spritesheet.png","iconPosition":"-272px -576px","iconClassName":"ctm-icon11731","logoIconClass":"icon11731","pros":["ブランディは、今なおコンテンツを作り続けている真のポルノ界のベテランだ","彼女はポルノ業界で最も象徴的な熟女クーガーの一人","複数のニッチにまたがる膨大なポルノシーンの数々","彼女は真のbbc好きで、黒人のチンコで本当にワイルドになる。"],"cons":["一部のファンにとって、彼女の政治と社会人としてのキャリアはしばしば否定的に衝突する。"],"detailedDescription":"<p>ポルノのニッチといえば、熟女ジャンルほどチンポを硬くし、まさに手強いものはない。巨乳のクーガーが18歳以上の若い男たちを迷わせ、年上の女性が太ももの間に秘める性の秘密を見せつけるのは、何とも魅力的だ。</p><p></p><p>確かに、硬いチンポをアナルに深く挿入するのが好きな18歳は楽しいが、誰もがファックしたいと思う性経験豊富なママには単純に太刀打ちできない。AV界における熟女需要の急増により、男たちの欲望を満たすためにハイヒールを履いてリングに上がるムラムラしたママたちが続々と登場するようになったが、そのなかには他よりはるかに優れた熟女もいる。</p><p></p><p>熟女AVのファンにとって、ブランディ・ラブは、彼女を見るたびにファンのチンコを勃起させてやまない、一目でそれとわかる名前の一人だ。彼女は、ゴージャスな偽乳とフェラチオの目という古典的なクーガー・ルックを揺らすだけでなく、セックスへの愛をカメラに放ち、あなたの肉棒を打ちのめすことを恐れない筋金入りのニンフォでもある。</p><p></p><p>しかし、ブランディ・ラブの熱心なファンでさえ、彼女のコンテンツをめぐって筋金入りの熟女オナニー・セッションに直行するため、彼女のキャリアに関する重要な事実を見落としていることに気づく。というのも、この少女は最も象徴的なポルノ女優の一人であり、ザーメン漬けのキャリアは魅力的な読み物になるからだ。</p><p></p><p>今日、私は彼女のパンティーを脇に寄せ、彼女の生い立ち、目を見張るようなポルノ出演、アダルト業界のキャリアに関する魅力的な事実、そして彼女が最近何をしているのかを深く掘り下げながら、あなたが今まで見たことのないブランディ・ラブをお見せしよう。</p><p></p><p>この魅惑的な熟女クーガーを発見したばかりの人も、彼女のAVコンテンツの熱烈なファンも、これは見逃せないブランディ・ラブの究極ガイドだ！彼女は自分を''Stifflerのママより良い''と売り込んでいる！</p><p></p><p></p><h3>ブランディ・ラブって誰？</h3><p></p><p></p><p>セントラル・ミシガン大学を卒業後、ブランディはワイン製造のビジネスに手を出したが、その後、別の種類のブドウからジュースを搾ることに目覚めた。2003年、彼女はアマチュア・ポルノのウェブサイトを立ち上げ、その後、激しいポルノ・キャリアの基礎を築いた。</p><p></p><p>2006年までに、ブランディは有名なポルノ業界の起業家で男優のクリス・ポトスキーと結婚し、二人はファルコン・フォトと協力して、ネイキッド・ライノ・メディアというニッチなポルノサイトを立ち上げた。</p><p></p><p>ブランディ・ラブの象徴的な熟女の容姿は、100以上のポルノスタジオに注目された。AVキャリアを通じて、彼女は異人種間、ホットワイフ、女の子同士、輪姦など複数のニッチAVにまたがる370以上のシーンに出演した。</p><p></p><p>彼女のポルノ出演は冗談ではなく、ブランディ・ラブは常に自分の演技に心、魂、そしてオマンコを注ぎ込んでいた。そのキャリアを通じて、彼女はAVNとXRCOの殿堂入りを果たし、熟女とクーガーの分野を中心に複数のアダルト業界賞を受賞した。</p><p></p><p>さて、彼女のバックストーリーを知った皆さんは、ブランディが多くの名声とポルノ賞を獲得した、前述のポルノ・パフォーマンスのいくつかに深く潜り込みたいと思うに違いない。さて、私はあなたを彼女のバーチャルなオマンコに顔から押し込んで、彼女の最もワイルドなポルノ演技のいくつかをお見せしますから、恐れることはありません！</p><p></p><p></p><h3>ブランディ・ラブ、必見のAVシーン</h3><p></p><p></p><p>この象徴的な熟女の淫乱ぶりをお見せするために、私はブランディ・ラブのAVマラソンにどっぷり浸かり、彼女の出演シーンを片っ端から見て、彼女の最高傑作をお届けすることにした。</p><p></p><p>● ブランディ・ラブは、BBCのポルノスター、アントン・ハーデンと共演したBlacked.comのスウィンギングポルノ作品で、彼女の内なるチンコへの欲望と同じ色の高価な黒いランジェリーを身に着けていた。アントンの巨大な黒チンポを前にすると、ブランディは我を忘れてしまう。彼女の濡れた熟女アソコは、この巨大なBBCによって大きく開かれ、彼女は忘我の淵に骨抜きにされる。</p><p>● Brandi Love Meets Mandingo - ラテックスの太ももハイを履き、BBCを崇拝する巨乳ブロンド熟女は楽しそうだ（実際そうだ）。この黒人の巨根は、大抵の女の子をタップアウトさせるのに十分な大きさだが、このハードコアママは40分以上にわたって玉の奥深くまで咥えることができ、この異人種ポルノシーンは忘れられないだろう！</p><p>● ブランディ・ラブの女同士のシーンが見たい？それならアイコニックなアドリアナ・チェチク以外に誰がいい？そう、この『One Last Time』は、ブランディとアドリアナの悪名高い2人のアソコが、激しいシザリングで押し付け合い、その後にお互いのクリトリスに舌を出し合うという、見逃せないレズビアン・ポルノ・シーンなのだ。残念なことに、チェチックは潮吹きで部屋を塗りつぶすことはない！</p><p>● キャプテン・ラブ - アホイ！MomLoverのこのシーンでブランディは、18歳の若い男たちに航海術を教える熟女船長のコスプレをした。しかし彼女は、バミューダトライアングルの航海術を教える代わりに、熟女ボディの航海術を教え、0から100までファックしまくる海上3Pをスタートさせる！彼女のアソコは十分に満足し、彼女は2人の新しい船員からダブルフェイシャルを受けるために膝をつく。その日、海には少し塩気があったと言ってもいいだろう！</p><p></p><p></p><h3>ブランディ・ラブの興味深い事実</h3><p></p><p></p><p>例えば、ブランディ・ラブは、推定数百万ドルの純資産を持つ、アダルト業界で最も稼いだ女優の一人と広く考えられている。</p><p></p><p>そして、ブランディ・ラブ／トレイシー・リン・リバモアは、株式トレーダー、ジェシー・リバモアのひ孫だということをご存知だろうか？彼女の曾祖父は元祖『ウォール街の狼』であり、デイトレードのパイオニアの一人として知られ、絶頂期には地球上で最も裕福な男の一人となった。</p><p></p><p>ブランディ・ラブは政治活動にも積極的で、ドナルド・トランプを支持する声高な保守派・共和党員である。彼女は保守系雑誌のオンライン版にも記事を書いている。2021年にターニング・ポイントUSAの会議に出席した際、未成年者が会議に参加していたことがラブのキャリアと衝突し、グロイパーズと呼ばれる右翼ナショナリストのグループに追い出された。</p><p></p><p>Newsweek』誌とのインタビューで、ラブは2024年の米大統領選挙についての考えを語り、トランプが2期目の出馬を断念した場合、フロリダ州知事のロン・デサンティスによる大統領選挙を支持すると語った。</p><p></p><p></p><h3>彼女のポルノの才能トップ3とは？</h3><p></p><p></p><p>● 熟女の乳首責め-この象徴的な熟女は、大きなママの乳首の真の定義を持っており、オイル漬けの乳首責めで最大限の効果を発揮する方法を的確に心得ている。彼女のお気に入りのテクニックのひとつは、スポーツブラを使って幸運な男のチンコをおっぱいの間に閉じ込め、巨大なおっぱいがジジーにまみれるまでその上で上下に跳ねることだ！</p><p>● 雑なフェイシャル - ザーメンフェイシャルは、特にザーメンを心から愛していないポルノ女優にとっては、マスターできない芸術だ。一方、ブランディは、彼女の完璧なメイクがザーメンが飛び散って台無しになる中、膝をついて口を開け、共演男性の目を見つめるのを忘れない。</p><p>● ダブル・ペネトレーション-50代になって変態的な経験をたくさん積むと、DPのようなものが自分をイカせるためのセックスの定番になるが、ブランディはこれをマスターしている。前腕よりも大きな2本の黒チンを同時にアソコとアナルに侵入させても、3本目のチンコを口に詰め込み、笑顔でカメラの奥を睨みつける。象徴的だ！</p><p></p><p></p><h3>ブランディ・ラブは今どこで何をしているのか？</h3><p></p><p></p><p>公式Twitterアカウントによると、彼女は現在、暖かいフロリダに住んでおり、OnlyFansのアカウントとTiktokのプロフィールを持っている。彼女のツイッターアカウントの最近の投稿によると、彼女は象徴的なボクサー、マイク・タイソンのファンでもある。これはぜひ見てみたい異人種間のシーンだ！</p>"}},{"id":"3a74ce76cb7b","collection":"sites_ja","data":{"slug":"3a74ce76cb7b","title":"Pamsnusnu","lang":"ja","date":"2025-10-29T00:00:00.000Z","description":"Pamsnusnuは、さまざまな場所でワイルドなスリルをリリースし、唯一のファンアカウントで独占的なコンテンツを提供する情熱的なスペインのポルノです。","canonical":"https://theporndude.com/zh/11718/pamsnusnu","affiliate_url":"https://fansly.com/r/missavdh?redirect=PamSnuSnu","rating":4,"siteOrder":6,"price":"free","tags":[],"features":[],"categories":[{"id":"best-fansly-girls-list-reviews","collection":"categories_ja"}],"screenshot_url":"https://cdn.staticstack.net/assets/img/r-thumbs/ba671_pamsnusnu_small.jpg","image_alt":"Pamsnusnu、ベストファンリーガールズリスト","scraped_at":"2025-10-29T13:43:44.047Z","iconSpritesheet":"custom-favicon-spritesheet.png","iconPosition":"-192px -576px","iconClassName":"ctm-icon11718","logoIconClass":"icon11718","pros":["動画のカメラアングルが良い","アナルシーンの量が多い","ほとんどのコンテンツがハードコアである。"],"cons":["オナニーのしすぎでチンコが痛い"],"detailedDescription":"<p>Pamsnusnuポルノ！おい、そこのムラムラしたオカマども！ワイルドな旅に出る準備はいいか？あなたの世界を揺るがし、チンコを弛緩させるスペインのポルノカップルを紹介しよう。Pamsnusnuを紹介しよう。このダイナミックなデュオは、リアルで生々しいハードコアアクションが売りだ。</p><p></p><p>この二人は普通のポルノスターではなく、本物だ。彼らは、最も親密な瞬間を記録し、喘ぎ声、笑い声、快感に満ちた叫び声をすべて撮影し、あなたの視聴の喜びのために繁栄している。ああ、彼らは楽しい時間を過ごす方法を知っていて、そのすべてをあなたと分かち合いたいのだ。人生は大変かもしれないが、Pamsnusnuはあなたに究極の逃避行を提供するためにここにいる。彼らのビデオを見ている間、あなたを爆睡させることに全力を注いでいるのだ。</p><p></p><p></p><h3>パムに注目</h3><p></p><p></p><p>パムはワイルドでセクシーなスペイン人の尻軽女。彼女のセックスアピールは桁外れで、彼女はあなたの膝を弱くさせるために彼女の資産を使用する方法を正確に知っています。彼女のむせ返るような視線から魅惑的な動きまで、彼女はあっという間にあなたを虜にしてしまうだろう。一度目にすれば、この爆乳美女の魅力に抗えず、虜になってしまうだろう。</p><p></p><p>パムの資産は魅惑的な光景であり、あなたを魅了する真の力である。彼女のおっぱいは完璧の一言に尽き、熟した果実のように瑞々しく、味わいたいと言わんばかりだ。一度目にしたら、その魅惑的な美しさに抗うことはできないだろう。</p><p></p><p>パムのお尻は快楽の遊び場のようで、彼女はあなたを欲望で狂わせる使い方を熟知している。魅惑的なトワークであなたをからかおうが、激しいセックスシーンでその栄光のすべてを見せつけようが、そのピクピクしたお尻は毎回ショーの主役だ。</p><p></p><p>パムはそのブーツの扱い方を熟知しており、それを披露することを恐れない。その魅惑的なツイストとトゥワークのたびに、あなたは彼女の魔法にかけられ、手を伸ばして戯れにお尻を叩いてみたくなることだろう。一度彼女の魅惑的なお尻を見たら、パムのスチーム・パフォーマンスの虜になり、もっと見たくなること間違いなし。さあ、ローションを持って、一生に一度のショーに備えよう！パムはあなたの心を揺さぶり、もっともっととおねだりすることでしょう。</p><p></p><p>パムは潮吹きクイーンでもあり、甘い蜜を滝のように流す方法を知っている。潮を吹くと、パムは快楽の豪雨を放ち、あなたを欲望でびしょ濡れにする。</p><p></p><p>彼女が恍惚の表情で身をよじり、うめき声を上げながらすべてを解放していく様は、どんな男でも欲望に狂わされるのに十分だ。彼女の潮吹きの才能の甘美な感覚を渇望しながら、何度も足を運んでしまうことだろう。</p><p></p><p></p><h3>スパニッシュポルノのワイルドでリアルな快楽の世界を解き放つ</h3><p></p><p></p><p>彼らのハードコアポルノビデオは、快楽のジェットコースターのようなもので、彼らはそれをすべて見せることを恐れていない。チンコが欲望でズキズキするような激しいフェラチオから、ハラハラドキドキさせられるようなアソコへのドキドキアクションまで、Pamsnusnuはあなたに猛烈な勃起を与えるパフォーマンスを提供する方法を知っている。</p><p></p><p>この大胆な恋人たちは、アナルシーンのスリリングな世界を探求することを恐れない。疼くような突きと快感のうめき声のたびに、彼らはあなたにもっとタイトなバックドアアクションをねだることだろう。</p><p></p><p>淫らな女狐パムは、アナルを激しく愉しみ、恍惚とした表情を浮かべる。それはまるで罪深い快楽のダンスのようであり、2人はそれを生々しいエネルギーで演じ、観客をハラハラさせ、もっとやりたいと切望させる。</p><p></p><p>しかし、まだある！Pamsnusnuは、普通の1対1のアクションだけでは満足せず、他のムラムラしたポルノカップルとチームを組んで、蒸し暑い4人組の楽しみのために、物事を一段上に持っていくのが好きです。</p><p></p><p>彼らは全く新しいレベルの快楽を手に入れ、爆発的な性的融合であらゆる快楽の組み合わせを探求する。彼らがパートナーを変え、快楽の渦に巻き込まれるのを見れば、あなたは疲れ知らずでチンコを撫でることになるだろう。</p><p></p><p>Pamsnusnuのコンテンツのほとんどはアマチュアで、リアルで本物であることを大切にしている。彼らの素人コンテンツは、ポルノ界の新鮮な空気のようなものだ。メインストリームのポルノビデオに見られるような、洗練された台本通りのでたらめなものは一切ない。Pamsnusnuでは、あなたが見るものは、生で、フィルタリングされていない、そしてとてもクソ熱いものです。</p><p></p><p>カメラアングルは完璧ではないかもしれないが、そこがいい。喘ぎ声も、突き上げも、快感の喘ぎ声も、まるでその場にいるような感覚になる。まるで自分もアクションの一部であるかのような爽快感だ。ビデオの画質も最高で、ぼやけたファジーなものは一切ない。</p><p></p><p></p><h3>セックスの冒険にあなたを誘う</h3><p></p><p></p><p>ホットな場所から別の場所へ、彼らはムラムラした遊牧民のカップルのように旅をし、快楽への飽くなき欲望と同じくらい多様な様々なアパートでファックする。ある瞬間、都会のロフトにいたかと思えば、次の瞬間には田舎の素朴な山小屋でエッチなことをしている。それはまるで世界中を飛び回る性的逃避行のようで、新しい経験に対する彼らの欲望の虜にならずにはいられない。</p><p></p><p>しかし、それだけではない！Pamsnusnuは物事を極端にすることを恐れないからです。彼らの衝撃的なビデオの1つでは、海のど真ん中で2人乗りのジェットスキーでファックしている！つまり、水しぶきを上げるということで、この2人はウェットでワイルドという全く新しいレベルの快楽を手に入れたのだ。</p><p></p><p>PamsnusnuはOnlyFansのアカウントも持っており、購読者はPamsnusnuの最もワイルドで親密な瞬間に独占的にアクセスできる。このエッチな恋人たちは、ファンをもっともっととおねだりさせ続ける方法を知っており、OnlyFansでは、彼女たちのギンギンに熱い逃避行の舞台裏を見ることができる。</p><p></p><p>OnlyFansを購読すれば、今まで見たこともないような無修正の露骨なコンテンツの宝庫を見ることができる。さらに、購読者はPamsnusnuと交流できる。</p><p></p><p></p><h3>ポルノ以外の人生</h3><p></p><p></p><p>美術館を訪れたり、美術展に足を運んだり、あるいは自分たちの芸術的な追求に没頭したりと、さまざまな形の芸術がもたらす美と表現を高く評価している。パムスヌはまた、ビーチへの強い情熱も共有している。彼らは日光浴をし、海の塩辛い抱擁を受け入れ、海岸線で忘れられない思い出を作るのが大好きだ。</p><p></p><p>彼らは料理が大好きで、もちろん健康的で健康的なライフスタイルを維持することの重要性を知っている。</p><p></p><p></p><h3>結論</h3><p></p>"}},{"id":"3a5a5a6e466d","collection":"sites_ja","data":{"slug":"3a5a5a6e466d","title":"Lara Rose","lang":"ja","date":"2025-10-29T00:00:00.000Z","description":"ララ・ローズは、巨大な自然の胸とふっくらしたお尻を持つ美しいブルネットです。彼女はオンラインで自分自身のさまざまなセクシーなビデオを投稿するのが大好きで、唯一のファンのファンでもあります","canonical":"https://theporndude.com/zh/14812/lararose","affiliate_url":"https://fansly.com/r/missavdh?redirect=laararose","rating":4,"siteOrder":7,"price":"free","tags":[],"features":[],"categories":[{"id":"best-fansly-girls-list-reviews","collection":"categories_ja"}],"screenshot_url":"https://cdn.staticstack.net/assets/img/r-thumbs/d2425_lararose_small.jpg","image_alt":"ララ・ローズ、ベストファンリーガールズリスト","scraped_at":"2025-10-29T13:44:01.636Z","iconSpritesheet":"custom-favicon-spritesheet.png","iconPosition":"-0 -736px","iconClassName":"ctm-icon14812","logoIconClass":"icon14812","pros":["小柄で曲線美","天然巨乳とピアス乳首","彼女はofをする。"],"cons":["彼女のof以外のコンテンツには、ときどきうんざりさせられることがある。"],"detailedDescription":"<p>ラナ・ローズのポルノ私は団塊の世代と呼ばれるかもしれないが、普段はあまりソーシャルメディアに時間を割かない。正直なところ、私は大ファンではない。もちろん、そう言うのはインスタグラムやその手のソーシャルメディアのことだ。でも、ララ・ローズのようなモデルのような美女を見つけるたびに考えが変わる。彼女のグッズをチェックするために、絶対に外に出るべきだと思う。</p><p></p><p>あなたは、私がいっぱいいっぱいだと思うかもしれないし、そう思うのは大歓迎だ。でも、私が言いたいのは、あなたはまだララ・ローズを見たことがないということ。このゴージャスな女性を見たら、すぐに考えが変わるはずだ。彼女は美しく、セクシーで、すべての場所に曲線がある。あなたが彼女と恋に落ちることは間違いない！</p><p></p><p>ララ・ローズは黒髪の美人で、巨乳といいお尻をしている。彼女は注目の的になるのが大好きで、彼女が提供するコンテンツはフェティッシュと言える。しかし、もしあなたがポルノだけを望んでいるのなら、Laraは適切な選択ではないかもしれない。この美女が18禁コンテンツを提供しないとは言っていない。</p><p></p><p>また、Lara Roseはポルノスターではないことも付け加えておきたい。彼女はOnlyFansを持っていて、頻繁に投稿するのが好きだ。でも、それらはすべて自作自演のエッチなものなので、プロフェッショナルなものに期待しないように。とにかく、彼女についてもっと知りたいなら、あなたは正しい場所に来た。ララ・ローズと彼女の美しさについて、すべてお話ししましょう。</p><p></p><p>もちろん、このムラムラの塊がお気に召さない場合は、他をご覧になっても結構です。この美女は、私がレビューした他の多くのゴージャスな女の子の一人に過ぎない。この美女をチェックする価値がないと思っても、他にもたくさんレビューしている。ぜひチェックしてみてください！</p><p></p><p></p><h3>ララ・ローズって誰？</h3><p></p><p></p><p>しばらく見ていると、彼女のビデオが出てきた。彼女もまた、ある卵をレビューしていた。基本的には、殻つきの卵をスクランブルして、ゆで卵にするというものだ。しかし、ララ・ローズは結果を見せずにビデオを終えてしまった。</p><p></p><p>そこで、彼女のプロフィールを訪ね、他の動画で結果を見ることを期待したが、クソの役にも立たなかった。彼女の他のビデオを見ているうちに、この女性は多くの男をムラムラさせるポテンシャルを持っていることに気づいた。つまり、彼女を見ただけでいい。ゴージャスで、セクシーで、下ネタが大好きで......少なくとも私はそう思っていた。</p><p></p><p>私には、女の子を見ただけで、その子がポルノ業界で大成する可能性があるかどうかを簡単に見分けるレーダーがある。さて、ララ・ローズが実際にポルノをやっているとは言わないが、彼女はOFコンテンツを提供している。彼女のコンテンツを探れば探るほど、エッチなものが増えていった。私は彼女の提供するすべてのグッズにとても満足しました...そしてあなたも満足すると思います。</p><p></p><p>さて、ララ・ローズって誰？私にはさっぱりわからない。彼女は20代で、今トレンドになっているコンテンツなら何でもやっているようだ。TikTokは彼女のレビューが中心で、InstagramとOnlyFansはかなりセクシーだ。さて、彼女のすべての情報を見つけることができたわけではないが、ララ・ローズがあなたの好みに合うかどうかを判断するのに十分な情報は間違いなく見つかった。</p><p></p><p>ララ・ローズについてもっと知りたければ、このまま読み進めてください。あるいは、自分で調べてもいい。また、彼女の個人的なことはあまり知りたくないが、ただ彼女のクソにアクセスしたいだけなら、彼女の名前をググればいい...いずれ見つかるだろう。</p><p></p><p></p><h3>OFにはホットなコンテンツがたくさん</h3><p></p><p></p><p>登録には3つの標準オプションがある。最初は1ヶ月の購読で5.59ドル。それから、3ヶ月のオプションで合計19.92ドル、6ヶ月のオプションで合計35.65ドル、12ヶ月のオプションで合計62.91ドル。どれを選ぶべきかは一目瞭然だろう。</p><p></p><p>これまでのところ、ララ・ローズの投稿数は約323、メディア数は340。そこでは、彼女がいろいろなことをするのを見ることができる。私が見たところ、Lara Roseにはボーイフレンドがいて、ウサギのようにセックスするのが好きなようだ。しかし、それ以上に、彼女は自分のカーブを見せるのが大好きなのだ。まだララ・ローズをググっていない人は、ぜひ。</p><p></p><p>ララ・ローズは、魅惑的な曲線を持つ小さな女の子だ。おっぱいもお尻も大きいけど、太ってはいない。少しぽっちゃりしているが、漫画のような体型だ。彼女の体格はこの世のものとは思えない。OFのビデオや画像では、彼女は巨大なおっぱいを弄るのが大好きだ。彼女は両乳首にピアスをしていて、それが彼女の美学にマッチしている。</p><p></p><p>彼女のビデオには、一人で楽しんでいるものもあれば、もっとハードコアなものもある。彼女がボーイフレンドにファックされるところを見ることができ、ボーイフレンドは彼の視点からすべてを撮影している。つまり、一般的なOFの内容に関しては、失望する人はいないと思う。ララ・ローズは自分のやっていることをよく知っているし、うまくやっている。</p><p></p><p>もちろん、彼女のコンテンツをこっそり見たければ、彼女のリークを検索すればいい。選択はあなた次第だ。多くのリーク系サイトがあるので、簡単に見つけることができる。それか、OFに直接行くか。彼女のコンテンツは間違いなく価値があると思う。</p><p></p><p></p><h3>キュートでセクシーなインスタグラム</h3><p></p><p></p><p>もちろん、実際のポルノを見ることはできない。インスタグラムなのだから！ポルノが見たいなら、OFに行けばいい。さて、誰でも彼女のインスタグラム・ページを閲覧することができる。面白いものもあれば、とてもエロティックなものもある。</p><p></p><p>彼女のインスタグラムを検索するなら、@larararosebで検索すれば見つかるはずだ。名前のBはバーチの略で、彼女のフルネームはララ・ローズ・バーチだと思うから。間違っているかもしれないが、普段は全く間違えない。彼女のインスタグラムにアクセスしたいなら、どうすればいいかわかるだろう。</p><p></p><p></p><h3>彼女のリンクはすべて彼女のツイッターで見つけることができる。</h3><p></p><p></p><p>また、彼女のツイッターにもアクセスすることができ、興味のある人はそこでセクシーな最新情報を得ることができる。彼女のすべてのメディアにアクセスすることができ、タイトな衣装で歩く彼女のリンクがよく見られる。また、彼女の他のリンクにもアクセスできる。</p><p></p><p>彼女のYouTubeは基本的にTikTokと同じだ。彼女はただ短い動画を投稿している。<strong>OFは彼女が本当に輝ける場所だと思うけど、彼女のヌードにお金を払うかどうか決める前に、ぜひララのソーシャルメディアをチェックしてみて</strong>。</p>"}},{"id":"28becbad0139","collection":"sites_ja","data":{"slug":"28becbad0139","title":"Fablazed","lang":"ja","date":"2025-10-29T00:00:00.000Z","description":"Fablazedは、アマチュアベネズエラの大人のアーティストです。彼女はラテンの血を抱きしめ、さまざまな癖を探求して、彼女の本当の気持ちで聴衆を引き付ける。","canonical":"https://theporndude.com/zh/11893/fablazed","affiliate_url":"https://fansly.com/r/missavdh?redirect=shirleycubas","rating":4,"siteOrder":8,"price":"free","tags":[],"features":[],"categories":[{"id":"best-fansly-girls-list-reviews","collection":"categories_ja"}],"screenshot_url":"https://cdn.staticstack.net/assets/img/r-thumbs/f688f_fablazed_small.jpg","image_alt":"fabり、最高のファンリーガールズリスト","scraped_at":"2025-10-29T13:44:12.270Z","iconSpritesheet":"custom-favicon-spritesheet.png","iconPosition":"-80px -592px","iconClassName":"ctm-icon11893","logoIconClass":"icon11893","pros":["彼女の身体はすべて自然である","彼女はソロプレイもセックスされるのも得意である","彼女は冒険好きで変態である。"],"cons":["彼女の潮吹きを見たことがない"],"detailedDescription":"<p>FablazedのAV！ベネズエラ出身の灼熱のAV女優、Fablazedを紹介しよう。ラテン系の魅惑的な魅力、魅惑的なブルネットの髪、そして自然な曲線美で、彼女はアダルト界に旋風を巻き起こした。Fablazedは単なるアダルトコンテンツ制作者ではなく、観客を虜にし、もっと見たいと思わせる方法を熟知した魅惑的な女性だ。彼女のスチームなパフォーマンスからソーシャルメディアでの積極的な存在感まで、Fablazedはスクリーンの内外でセンセーションを巻き起こしている。</p><p></p><p></p><h3>生い立ちとポルノへの参入</h3><p></p><p></p><p>ポルノの領域に狙いを定めたFablazedは、その奔放なパフォーマンスと生の才能で瞬く間に注目を集めた。ラテン系のルーツを生かし、本物の情熱とセンスを披露し、その奔放な情熱と快楽への飽くなき欲求で視聴者を魅了した。</p><p></p><p>唾吐きやゴールデンシャワーなど、フェティッシュなプレイにも積極的に挑戦し、境界線を押し広げ、彼女のパフォーマンスにさらなる興奮を与えている。彼女は見られているスリルを味わい、スクリーンの中の彼女の魅惑的な冒険に耽溺する観客を支配する力に喜びを感じている。</p><p></p><p></p><h3>スクリーンを燃え上がらせるFablazed</h3><p></p><p></p><p>強烈なアイコンタクト、魅惑的なオーラル・スキル、奔放な演技の魅力など、Fablazedの存在は視聴者の心とファンタジーに確実に残る。</p><p></p><p>一部のAV女優とは異なり、Fablazedは、彼女の愉快で自然なバストを含む自然な資産を誇らしげに誇示している。このベネズエラの女狐は、人工的な基準に合わせることなく、リアルであり続けることを信条としている。</p><p></p><p>Fablazedはラテン官能の真の精神を体現している。甘美なブルネットの髪が肩から流れ落ち、一目見ただけで無邪気な顔から拗ねたような顔まで簡単に切り替えられる顔を縁取っている。</p><p></p><p>彼女は、あなたの小さな乳首を撫でるためにローションのボトルに手を伸ばさせること間違いなしの激しさで、彼女の最も深い欲望を解き放つ。好きなことのひとつと称するフェラチオから、スパンキングされる爽快感、親密な瞬間のアイコンタクトまで、彼女は快楽のあらゆる面を探求することに躍起になっている。</p><p></p><p>Fablazedが後背位をするようになると、それは単なるセックス体位ではなくなる。彼女の巧みな指導は、日常を非日常に変え、パートナーをかつてないエクスタシーに喘がせる。しかし、それだけではなく、彼女には邪悪なひねりがある。</p><p></p><p>Fablazedは、唾とゴールデンシャワーの両方を含むエッチなプレイで物事をスパイスアップする特別な味を持っています。そう、その通り！彼女は、快楽のワイルドな側面を探求することを恐れず、すでに印象的な性的レパートリーにおいしく変態的なタッチを加えます。</p><p></p><p>また、あなたが緊縛に興味があるなら、彼女はあなたをスリリングな体験に誘うロープと拘束具を用意しています。ロールプレイや、支配と服従のダイナミクスを探求してみたい？彼女なら大丈夫。</p><p></p><p>Fablazedは彼女のコンテンツに多才さをもたらしている。このセクシーなラティーナ・アダルト・コンテンツ・クリエーターは、様々なシナリオに適応し、心を揺さぶるパフォーマンスを提供する方法を知っており、ファンの多様な欲求に応えている。彼女の魅惑的な腕前を際立たせるシズル感たっぷりのソロ・セッションであれ、快楽への飽くなき欲求を見せつける激しいボーイ・ガール・シーンであれ、Fablazedは、彼女がアダルト・エンターテイメントの世界における真のカメレオンであることを何度も証明している。</p><p></p><p>ご存じない方もいらっしゃるかもしれないが、Fablazedはソロプレイの女神であり、様々なセックスグッズをコンテンツに取り入れることで、ソロセッションを最大限に楽しむ方法を熟知している。ディルドからバイブレーター、クリトリス吸引器まで、彼女は究極の快楽を追求するために手を抜かない。</p><p></p><p>Fablazedは彼女のディルドのコレクションを持ち出し、視聴者にゾクゾクするような体験を提供する。優しく突こうが、力強く挿入しようが、彼女はあらゆるスポットにヒットする方法を熟知している。バイブレーターもFablazedのお気に入りの玩具の一つで、彼女はその使い方を熟知している。バイブレーターを手に、彼女は敏感な乳首からドキドキするクリトリスまで、体の隅々まで探ります。</p><p></p><p>脈打つ振動が彼女に快楽の波を送り込み、恍惚の表情で呻き、震え上がらせる。視聴者は彼女の快楽に満ちた旅を間近で見ることができ、もっと見たいと思うことだろう。</p><p></p><p>Fablazedのソロプレイ・コンテンツは、彼女の垂涎の的であるクリトリス吸引器を含めることで、興奮と快楽の全く新しいレベルに達する。ひとたびクリトリス吸引器を使うと、Fablazedの身体は快楽のシンフォニーのように反応する。ドキドキするクリトリスを優しく押されるたびに、彼女は部屋中に響き渡る歓喜の呻き声を漏らさずにはいられない。恍惚の表情で目を丸くし、つま先を丸めて悦びに浸る。</p><p></p><p>Fablazedはまた、スチームな女同士のコンテンツでも熱を帯びる。クリエイター仲間とのコラボレーションでも、友人との親密なひとときでも、Fablazedは魅惑的な唇と巧みな舌使いで相手の肌を滑らせ、ゆっくりと官能的な探求を始める方法を熟知している。</p><p></p><p>Fablazedはまた、彼女の柔らかいラテン系の指でパートナーを巧みに喜ばせ、くすぐる方法を知っており、あらゆる曲線と敏感なスポットを巧みに操り、彼女の共同制作者を欲望で震え上がらせる。彼女はまた、自分の体を相手の体に擦りつけながら巧みに絡み合わせ、魅惑的な映像の饗宴を作り上げる。</p><p></p><p></p><h3>ポルノ以外の人生</h3><p></p><p></p><p>Fablazedはまた、OnlyFansのアカウントも運営しており、毎日無修正のコンテンツをアップロードし、購読者を満足させている。</p><p></p><p>キーボードの上でナッツをブスブス鳴らすのに忙しいムラムラした負け犬のニーズに応えていないとき、彼女は彼女のリラックスしたのんきな性格を完璧に引き立てる様々な趣味にふけっている。Fablazedのお気に入りの趣味のひとつは、ビーチで日光浴をすること。</p><p></p><p>驚異的な体格とスタミナを維持するため、Fablazedはアクティブであることを好み、定期的にさまざまなエクササイズに取り組んでいる。ヨガから有酸素運動まで、彼女は体を最高の状態に保つことの重要性を理解している。根っからのグルメであるファブリーズドは、美味しいものを食べることにも喜びを感じている。新しい料理に挑戦する時も、お気に入りの料理を味わう時も、彼女は料理を楽しむ芸術を高く評価している。</p><p></p><p></p><h3>結論</h3><p></p>"}},{"id":"7e3ae2c92c9a","collection":"sites_ja","data":{"slug":"7e3ae2c92c9a","title":"Riley Reid","lang":"ja","date":"2025-10-29T00:00:00.000Z","description":"ライリー・リードは、賞を受賞したポルノスターであり、何百もの映画がストッキングの下にあります。この権威あるガイドは、最もワイルドな方法で彼女のポルノのキャリアに分かれています。","canonical":"https://theporndude.com/zh/11729/rileyreid","affiliate_url":"https://fansly.com/r/missavdh?redirect=rileyreidx3","rating":5,"siteOrder":9,"price":"free","tags":[],"features":[],"categories":[{"id":"best-fansly-girls-list-reviews","collection":"categories_ja"}],"screenshot_url":"https://cdn.staticstack.net/assets/img/r-thumbs/bde9f_rileyreid_small.jpg","image_alt":"ライリー・リード、ベストファンリーガールズリスト","scraped_at":"2025-10-29T13:44:20.143Z","iconSpritesheet":"custom-favicon-spritesheet.png","iconPosition":"-240px -576px","iconClassName":"ctm-icon11729","logoIconClass":"icon11729","pros":["nothing"],"cons":["nothing"],"detailedDescription":"<p>AVとは、ファンの性的妄想を可能な限り荒唐無稽な方法で実現させるものだ。性的に堕落した義理の母親が義理の息子のチンコに馬乗りになるのを見たい人も、大学を中退したばかりのキュートで清純そうな女の子が、学位取得の願望をすべてかなぐり捨てて、画面の中のチンコを崇拝するのを見たい人も、AVならカバーできる！</p><p></p><p>後者のヤリマンについては、18歳や19歳になったとたんにハードコアAVに真っ先に飛び込む女の子たちが、AV業界には後を絶たない。彼女たちは、できるだけ早くAVのキャリアをスタートさせ、ハードコア・セックスについてできるだけ早く学びたいのだ。ライリー・リードがその典型だ！</p><p></p><p>ライリー・リードをまだ知らない人は、どんな岩の下で生きてきたのか知りたくない。一方、彼女の名前を聞いたことがあっても、19歳で濡れそぼったマンコで業界に飛び込んだこのポルノ娼婦について、知らないワイルドなことがいくつもあることは保証できる。</p><p></p><p>今日、私はあなたが今まで見たことがないようなライリー・リードについてのポルノスターの洞察を突き刺します。このポルノスターのプロフィールは、知られざる事実や彼女の最も象徴的なポルノシーンから、ポルノ業界における最も素晴らしい才能、そして最も重要なことは、どこで彼女の栄光のすべてを見ることができるかまで、すべてをお見せします！</p><p></p><p>このチンポに飢えた娼婦は、スクリーン上でのチンポ処理能力で47ものアダルト業界賞を受賞している。さあ、彼女のパンティの裏側に潜入して、その素顔を確かめてみよう。ポルノの女神、ライリー・リードへの究極のガイドに備えよう！</p><p></p><p></p><h3>ライリー・リードとは？</h3><p></p><p></p><p>リードはフロリダで生まれ、アイルランド系、プエルトリコ系、ドミニカ系の血が混じっている。その炎の源はそこにあるのだ！彼女はスリムで小柄、身長170cm。</p><p></p><p>多くのポルノ女優がそうであるように、ライリーがアダルト業界に入ったのは、ストリップ・クラブでエロティック・ダンサーとして働いたのが最初だった。彼女が数年後にポルノ界のスターダムにのし上がるのを見る幸運な男たちの一人であることを想像してみてほしい。</p><p></p><p>ライリー・リードがポルノ業界に足を踏み入れたのは2010年、彼女が19歳の時だった。当初、彼女のポルノスターの名前は、あまりキャッチーでないペイジ・ライリーだった。3年後、彼女の演技はすでにポルノ界の注目を集め、LAウィークリー誌の記事「次のジェナ・ジェイムソンになるかもしれない10人のポルノスター」で8位にランクインした。同年、彼女はXBIZ賞の2013年最優秀新人女優賞を受賞した。</p><p></p><p>CNBCが毎年発表している \"The Dirty Dozen \"というリストをご存知だろうか：ポルノ界で最も人気のあるスターたち」。ライリーは2014年、2015年、2016年と3年連続でそのリストに名を連ねている。そう、彼女は時間を無駄にすることなく、特にワイルドなポルノキャリアの基礎を築いたのだ！</p><p></p><p>でも、どれくらいワイルドだったのでしょう？次に、ライリー・リードの最もハードコアなポルノ演技を紹介したい。このポルノ女優を知ったばかりの人も、初日から彼女を追いかけている人も、このリストは彼女の最高傑作を知る上で見逃せないものだ！</p><p></p><p></p><h3>ライリー・リード（Riley Reid）の必見AVシーン</h3><p></p><p></p><p>というわけで、誰もが一度は見るべきライリー・リードのベストシーンを探すというミッションのもと、極度のオナニーマラソンでこのリストを効率化することにしよう！</p><p></p><p>● シャネル・プレストンがライリー・リードをいかがわしいセックス・ショップに連れてきたとき』--これはライリーの出演シーンの中で私が最も好きなもののひとつで、手強いシャネル・プレストンに哀れな淫乱サブに仕立て上げられ、いかがわしいアダルト・ショップに連れ込まれて客全員とファックするシーンだ。このシーンでは、彼女はシャネル・プレストンによって哀れな淫乱サブに仕立て上げられ、いかがわしいアダルトショップに連れ込まれて客全員とセックスさせられる！強制オーガズム、縛りファック、女同士、喉ファック、そしてその間にあるものすべてだ。私のお気に入りのシーンは、店のカーペットからこぼれたザーメンを貪るライリーの姿。実にいやらしい！</p><p>● ジュールズ・ジョーダンの『ライリー・リード異人種輪姦』-ライリーがこのシーンでバージンの白いランジェリーを着ていたのは皮肉だ！このシーンにBBCが何人出てくるか数え切れないが、かなりの数で、彼らはライリーのタイトで小さな穴を、想像できる限り最もワイルドな方法で時間を無駄にすることなく引き延ばしていく。このシーンの特徴である執拗なダブル挿入ファックの間、彼女のキュートな顔に巻き起こるクロス目のオーガズムは、まさに絶大だ！</p><p>● ライリー・リード・フェムドム - このシーンは、ライリーがいかにポルノのニッチを極めることができるかを示す典型的な例であり、彼女はファックされるのと同じくらい激しく男の尻をファックする能力を証明する。貞操の檻の中でベッドに縛られた従順な男性は、ライリーの顔にペニスを縛り付けられ、ライリーが彼の上でクンニするまで騎乗される。その後、ライリーは彼の奉仕に感謝するため、彼を屈ませ、彼女のアソコ汁で潤滑された同じストラップオン・チンポで彼の尻を犯す。彼女は小柄で、クソ可愛く見えるが、ライリーはこの男を牝犬のように啼かせる！</p><p></p><p></p><h3>ライリー・リードについての興味深い事実</h3><p></p><p></p><p>まず、ライリー・リードは、2013年に最優秀新人女優賞を受賞し、2014年には年間最優秀女性パフォーマー賞を受賞した。</p><p></p><p>彼女はまた、Evil Angel、Mile High、Smash Pictures、Elegant Angel、Brazzers、Jules Jordan Videoなど、世界的なポルノの大物にもフィーチャーされている。</p><p></p><p><strong>ライリー・リードは、水を得たアヒルのようにどんなニッチなポルノにも馴染むタイプの尻軽女で、その典型的な例が、『Mandingo Massacre 6』というタイトルにふさわしく、複数の黒人のチンコを相手にする初の異人種間セックスシーンでAVN賞を受賞</strong>したことだ。</p><p></p><p>ライリーは長年にわたり、元カレたちはみんなアンチポルノだったと主張してきた。元カレたちはしばしば、ポルノより自分たちを選ぶように仕向け、ライリーはいつもポルノを選んだという。よくやった、ライリー！</p><p></p><p></p><h3>彼女のポルノの才能トップ3は？</h3><p></p><p></p><p>● 潮吹き-ライリー・リードには、これまでに見た中で最高の潮吹きポルノをプロデュースする才能があり、彼女の最高傑作シーンの1つでは、白とピンクのストッキングを履きながら、ドクドクと脈打つポルノチンポンに乗って、透明な汁を容赦なく噴出させた。この男はレインコートを着るべきだった！</p><p>● ライリーは、化粧と高価なランジェリーに身を包むと神々しく見えるが、彼女は危険を顧みず、人が知る限り最も不潔なディープスロート・フェラチオを披露する。</p><p>● ディック・ライディング - この淫乱女は弾ける！ライリーは、チンコの上で跳ねたり、スタミナを試すのが大好きな体育会系の女の子。硬いチンコを滑らせる彼女のヌルヌルマンコに飽きたら、北京語が読めるなら、彼女の背中に彫られた漢字のタトゥーを読めばいい！</p><p></p><p></p><h3>ライリー・リードは今どこで何をしているのか？</h3><p></p><p></p><p>彼女は現在もポルノ業界で活躍しているだけでなく、ポルノ撮影の舞台裏や風俗業界を中心とした様々な重要なトピックをカバーする著名なYoutuberでもある。</p><p></p><p>2021年、ライリー・リードはフリーランナーのパシャ・ペトクンスと結婚し、その後二人の間に娘が生まれたので、彼女が女同士のAVに転向した後、交際の問題はすぐに解決したようだ！</p><p></p><p></p><h3>ライリー・リードのポルノを見るのに最適な場所は？</h3><p></p>"}},{"id":"274c7afca904","collection":"sites_ja","data":{"slug":"274c7afca904","title":"SofiCute","lang":"ja","date":"2025-10-29T00:00:00.000Z","description":"Soficute1234Sファンリーはあなたの夢の愚かなティーザーですが、40ドルの月額料金は、あなたが購入する太もものギャップに包まれた赤い旗です。","canonical":"https://theporndude.com/zh/23817/soficute-fansly-review","affiliate_url":"https://fansly.com/r/missavdh?redirect=soficute1234","rating":3,"siteOrder":10,"price":"free","tags":[],"features":[],"categories":[{"id":"best-fansly-girls-list-reviews","collection":"categories_ja"}],"screenshot_url":"https://cdn.staticstack.net/assets/img/r-thumbs/4e50d_soficute-fansly-review_small.jpg","image_alt":"柔軟で、最高のファンリーガールズリスト","scraped_at":"2025-10-29T13:44:29.922Z","iconSpritesheet":"default","logoIconClass":"icon1006","pros":["エキシビジョニスト・エネルギー"],"cons":["週1回の写真で月40ドル","写真7枚とビデオ2本の小規模ライブラリ"],"detailedDescription":"<p>そんなわけで、Fanslyの暗い隙間をスクロールしていると、「SofiCute1234」という警告ラベルが貼られるべきほど甘美な名前を持つキュートなブルネットに出くわした。姪っ子のRobloxユーザー名みたいでしょ？違う。5秒後には、まるで呪われた不潔の宝箱を開けたかのように、シャツから汗が吹き出てくるのだから。彼女のページは控えめで、物腰が柔らかく、おっとりしてさえいる：\"18歳のとき、初めてカメラの前で裸になりました。その瞬間、オーガズムのような感覚を覚えました。\"なんだって？ただのセリフじゃない。ヤリマン文学のイエスになる瞬間だ。誰がそんなことを軽々しく言うんだ？キラキラを散りばめた変態宣言だ。そして突然、私はすべてを手に入れた。通知をチェックしていた次の瞬間には、デジタルアライグマのようにこの女の子のメディアフィードにどっぷり浸かっていた。</p><p></p><p>この一文だけで、ポルノ史に刻まれるはずだ。どうしてTシャツに書かれたり、負け犬の太ももにタトゥーされたりしないんだろう？生々しくて、恥知らずで、知るべきことをすべて教えてくれる。この女は？彼女はこのクソのために作られた。彼女は偶然ヌードに出くわしたんじゃない。それは、私のペニスを実存的恐怖で痙攣させる性的自己認識のレベルだ。表面下にはもっと堕落したものが埋もれていて、シャベルが欲しいくらいだ。彼女の雰囲気はベテランポルノ女優のそれではないが、可能性を匂わせる。彼女は隣の家の少女ではない。カーテンを開けっ放しにして、見つめられると微笑む隣の家の少女だ。教えてあげよう。ソフィはまだポルノ帝国を築き上げたわけではないが、パンティーを履いたまま種を蒔いている。今は確かにソフトコアだが、ハングリー精神はある。彼女の経歴にあるセリフ？あれは淫らな予言であり、私はそれが成就するのを見るつもりだ。</p><p></p><p></p><h3>少ない人数、高い報酬</h3><p></p><p></p><p>彼女はチャットする。彼女は返信する。夜中の3時にでも、まるでスケベな同人誌を現実にしたかのようにイチャついてくる。そして、大女優から得られるようなロボットのようなコピペのクズでもない。ここには努力がある。生々しさ。社会的なぎこちなさが、彼女を10倍ホットにしている。クラスでホットなオタクが、ヨガパンツをはいて前かがみになるのがいかに似合うかを発見し、それをさらに探求する手助けをしてほしいと思っているように、彼女は伝わってくるのだ。さらにホットなのは？彼女は見られることに興奮するんだ。そう。それが彼女のすべて。彼女は、自分が人間のザーメンキャンバスのように見つめられているのを知るのが好きなんだ。あなたが彼女を \"売春婦 \"と呼ぶと、彼女は顔を赤らめ、唇を噛みしめて \"もっとゆっくり言って \"と言うような女よ。</p><p></p><p>彼女は覗き見を生きがいにしている。その視線？お母さんの家の地下室でHENTAIを見ながら、あなたが完成させた、変態的で、よだれを垂らし、脳みそを蝕むような視線？彼女はそれが大好きなんだ。それは彼女を興奮させ、彼女が明らかに女神になるために生まれてきたように感じさせる。お金のためじゃない。お金のためだけじゃない。注目されることで、フロリダの雷雨よりも濡れてしまうからだ。だから、目を釘付けにしとけよ、サル男。彼女は君がいつも求めていた露出狂のアニメ・ワイフだ。そして、もし君が賢いなら、彼女が爆発して君の哀れな小さなユーザー名を忘れる前に、ここに留まるだろう。</p><p></p><p></p><h3>私のバックのための地獄のバングはどこにありますか？</h3><p></p><p></p><p>では、その大金で何が手に入るのか？毎週日曜日にセクシーな写真を1枚。それだけだ。たった一枚。たった一枚。写真。毎週。そして彼女とチャットするオプション。でも、彼女はすでに下の層でそうしている。それなのに36ドルも払う必要があるのか？彼女がHDであなたを無視していることを知る名誉？彼女はキュートだ。彼女がランジェリー姿で足の爪を切るのを喜んで見るよ。でも、彼女のメディア・ライブラリーが7枚の写真と2本のビデオなのに、この値段は犯罪的だ。その通り。これは保管庫じゃない。誰かがアップロードし忘れたDropboxのフォルダだ。</p><p></p><p>これは私が怒りでやめるべきポイントだ。ノートパソコンをパタンと閉じて、隣の家の壁のペンキが乾くのを眺めるような、もっと充実したことで自分を奮い立たせるべきところだ。でも問題はここからだ。ソフィーには奇妙な支配力がある。あの \"初めて裸になった時の私 \"のエネルギーは、ポルノ詩のように頭にこびりついて離れない。彼女は中毒性があり、それを知っている。彼女はコンテンツを投下するためにここにいるのではない。彼女は長いゲームをしているのだ。イジる。構築。彼女は、あまりに多くのものを、あまりに早く与えてしまうと、力を失ってしまうことを知っている。だから彼女は、食卓の餌をねだる犬のように、あなたを夢中にさせるのだ。</p><p></p><p></p><h3>たぶん40ドル？</h3><p></p><p></p><p>そう、彼女はアクティブで、反応もよく、あなたが彼女の受信トレイで大きな息をすれば、「おはよう、ベイビー」と送ってくれるかもしれない。しかし、ここに厳しい真実がある：それは値札を正当化するものではありません。あなたは、中級の親密さのためにプレミアム料金を支払っているのだ。生コンテンツも、フルアクセスのギャラリーも、ポルノらしきものも手に入らない。得られるのは、つながりの幻想だ。受信トレイに届く魅惑的なささやきや、彼女が気にかけていると妄想させる軽薄な絵文字。そして、正直に言おう-私たちは皆、一度や二度はそれに騙されたことがある。しかし、\"ヘイ、カワイコちゃん \"と言った後、ゴーストになるために40ドルも払ったことに気づけば、そのドーパミンの高揚感は長くは続かない。</p><p></p><p>彼女のハッスルを非難してるわけじゃない。ソフィーがファックのように立派なのは間違いない。<strong>彼女は、幻覚でないことを確認するために、二度見、瞬き、そしてもう一度見てしまうような体つきをしている</strong>。太もも、ウエスト、彼女の体のラインの取り方は、ガラス張りのパン屋を前にした飢えた男のような気分にさせる。しかし、肉体的な魅力だけでは契約は成立しない。もはやそうではない。半額でオモチャを穴に突っ込んで、あなたの名前を言ってくれる淫乱女が市場に溢れかえっている今、そうはいかない。熱狂させるか、価格を下げるかだ。今、彼女はそのどちらもしていない。</p>"}},{"id":"4af957016a76","collection":"sites_ja","data":{"slug":"4af957016a76","title":"Cherry Crush","lang":"ja","date":"2025-10-29T00:00:00.000Z","description":"チェリークラッシュは才能のあるASMRアーティストであり、最終的に彼女のコンテンツに属しているのは、あなたの興味をリラックスさせ、興奮させる唯一のファンで彼女のコンテンツに属していることに気付きました。それはあなたがその時に必要なものに依存します","canonical":"https://theporndude.com/zh/14797/cherrycrush","affiliate_url":"https://fansly.com/r/missavdh?redirect=cherrycrush","rating":4,"siteOrder":11,"price":"free","tags":[],"features":[],"categories":[{"id":"best-fansly-girls-list-reviews","collection":"categories_ja"}],"screenshot_url":"https://cdn.staticstack.net/assets/img/r-thumbs/4ec1b_cherrycrush_small.jpg","image_alt":"チェリークラッシュ、ベストファンリーガールズリスト","scraped_at":"2025-10-29T13:44:38.142Z","iconSpritesheet":"custom-favicon-spritesheet.png","iconPosition":"-432px -720px","iconClassName":"ctm-icon14797","logoIconClass":"icon14797","pros":["asmrの才能","あなたの耳とペニスを興奮させる","信じられない体"],"cons":["ハードコア・ポルノは禁止"],"detailedDescription":"<p>Cherry Crushのポルノ！チェリー・クラッシュは、癒し系の声を持つピンク髪の美女で、どこからともなく現れ、多くのファンを獲得したようだ。しかし、彼女は一夜限りのセンセーションではない。彼女は何年も芸を磨いてきたのだ。</p><p></p><p>チェリー・クラッシュはフロリダで育った。チェリーは常にASMRとリラックスできるコンテンツ作りに魅了されていた。彼女はASMRのYouTubeチャンネルを立ち上げ、徐々に人気を集めていった。卒業後、チェリーはすぐにアダルト・エンターテイメントの世界に飛び込んだ。</p><p></p><p></p><h3>見た目通りのセクシーさ</h3><p></p><p>プラチナブロンドのロングヘアが肩にかかり、エメラルドグリーンの瞳、ふっくらとした唇はいつもピンク色。完璧な陶器の肌には、鼻と頬にそばかすが点在している。</p><p></p><p>チェリーは冷静でのんびりしたスタイルで知られている。撮影していないときは、レギンス、オーバーサイズのTシャツかスウェットシャツ、スニーカーといった快適な服装でいることが多い。しかし、ライブストリーミングやビデオでは、ランジェリー、クロップトップス、ミニスカート、ボディコンドレスといったセクシーな服装を選び、ファンのために豊満な曲線を披露する。チェリーは、カメラに向かって自分の資産を誇示する方法をよく知っている。</p><p></p><p>チェリーがOnlyFansで最もホットなモデルの一人になったのも不思議ではない。魅力的なルックスとそれに見合った性格で、彼女は視聴者を魅了し、もっと見たいと思わせる。チェリーの魅力的な外見と媚びない魅力は、彼女の幅広い魅力と成功の大きな部分を占めている。</p><p></p><p></p><h3>ASMR</h3><p></p><p></p><p>1年も経たないうちに、彼女のチャンネルの人気は急上昇した。チェリーは自分のニッチを見つけ、パーソナライズされたASMR体験を作り出した。ファンたちは、自分のために作られたビデオのように感じさせる彼女の能力を称賛した。</p><p></p><p>今では100万人以上のYouTube登録者が、彼女の最新のASMR作品を心待ちにしている。彼女のささやくような声と優しいサウンドは、何百万人もの人々に安らぎをもたらしてきた。彼女のビデオは趣味として始まったが、チェリーの努力と情熱はフルタイムのキャリアとなった。彼女はYouTubeを通じて、他の人々がリラックスと喜びを見つけられるようなプラットフォームを築いてきた。</p><p></p><p>多くの人がチェリーに、YouTuberであることの一番の喜びは何かと尋ねる。チェリーは、視聴者とつながり、コミュニティを築くことをとても愛している。彼女は、自分の動画がどのように彼らの一日を明るくしたり、リラックスさせてくれるかというファンからのコメントを読むのが大好きだ。自分のコンテンツを通してポジティブさと喜びを広めることができることを知ることは、チェリーにとって非常にやりがいのあることなのだ。</p><p></p><p></p><h3>ポルノへのジャンプ</h3><p></p><p></p><p>数ヶ月のうちに、チェリーはOnlyFansから他の収入を合わせたよりも多くの収入を得るようになった。彼女は、コンテンツ制作への情熱をフルタイムのキャリアに変えるチャンスだと気づいたのです。</p><p></p><p></p><h3>OnlyFansのコンテンツの種類</h3><p></p><p></p><p>チェリーは、OnlyFansが提供するクリエイティブな自由を気に入っている。このプラットフォーム上で、彼女は独占的な写真やビデオを自分の言葉でファンと共有することができる。他のソーシャルメディア・プラットフォームのような厳しいコンテンツ・ルールやガイドラインを気にする必要はない。彼女のファンは、OnlyFansでのチェリーのありのままの姿を気に入っている。彼らは本物のチェリー・クラッシュを見ることができると感じている。</p><p></p><p></p><h3>ASMR論争</h3><p></p><p></p><p></p><h3>お気に入りのASMRの種類</h3><p></p><p></p><p>彼女が視聴者に散髪をしたり、メイクをしたり、マッサージをしたりするふりをするロールプレイ。このような想像力豊かなシナリオによって、彼女はリアルな音を作り出すことができる。</p><p></p><p>耳プレイと舐めること。女性に耳を舐められたり囁かれたりすると、ゾクゾクする男性は多い。現実にはそんなことをする女性はいませんから、チェリーに任せた方がいいでしょう。</p><p></p><p>羽毛、絵筆、キネティックサンド、スライム、グニャグニャのおもちゃなど、彼女が集めたさまざまなものを使って音を作り出す。軽い音、引っ掻く音、ぎゅっと握る音は、ASMRにとても効果的だ。</p><p></p><p>さまざまな音、小道具、シナリオを試すことで、チェリー・クラッシュは視聴者が最もリラックスでき、ゾクゾクするコンテンツの種類を見つけた。バラエティーに富んだコンテンツを制作することで、ASMRファンなら誰でも楽しめるものがあるのだ。</p><p></p><p></p><h3>トイズ・メイキング・トラブル</h3><p></p><p></p><p>ウーマナイザーは、吸引と脈動振動で強烈な感覚をもたらすクリトリス刺激器。</p><p></p><p>マジックワンド、強力な充電式ワンドバイブレーターで、クリトリスへの刺激と筋肉痛のマッサージの両方に使えます。</p><p></p><p>バットプラグは、アナルプレイのための様々なサイズがあり、秘密のスリルのために他の活動の間に着用することができます。</p><p></p><p>チェリーさんは、高品質で体に安全なおもちゃに投資し、自分の快感を得られるものを見つけるために実験を楽しむことをフォロワーに勧めている。セックスグッズは、自分自身やパートナーと一緒に使うことで、興奮とオーガズムを高めてくれる。</p><p></p><p></p><h3>チェリーとのデート</h3><p></p><p></p><p>完璧なデートでは、本当に心を通わせ、笑いを分かち合い、話を交換し、共通の話題を見つけることができます。ディナーを食べながら気まずい面談をするよりも、\"デート \"という側面からフォーカスを外し、ただお互いを楽しむようなアクティビティを好む。夜の終わりに、相性と会話が弾めば、ASMRのビデオを一緒に聴こうと誘ってくれるかもしれない。もっといいのは、あなた自身がビデオの一部になること。マカロニ・アンド・チーズをかき混ぜる」というタイトルかもしれない。</p><p></p><p>あるいは違うかもしれない。チェリー・クラッシュは、ファンの誰ともセックスはしないし、デートもしないと何度も言っている。ファンやフォロワーからのサポートには感謝しているが、プライベートと仕事は分けて考えたいという。彼女は、OnlyFansとASMRコンテンツを作ることが仕事であり、プロフェッショナルであることを目指していると語っている。何人かのファンからデートに誘われたり、交際を申し込まれたりしているが、彼女はこれまですべての申し出を断っている。</p><p></p><p></p><h3>ファンがチェリー・クラッシュを愛する理由</h3><p></p><p></p><p>彼女の甘く泡のような性格だ。チェリーはとてもフレンドリーで、心優しく、親近感がわくような人柄が動画から伝わってくる。友達になれそうな人だ。</p><p></p><p>彼女のASMRスキル。<strong>チェリーは、想像力豊かなASMRのロールプレイや、ゾクゾクするようなビデオを</strong>作ります。彼女の柔らかい声、優しく叩く音、ひっかく音はとてもリラックスさせてくれます。</p><p></p><p>彼女のオープンさ。チェリーは、趣味や日々の活動から人間関係や個人的な苦悩に至るまで、彼女の人生の詳細をファンと共有している。この信憑性と無防備さによって、視聴者は彼女と深いレベルでつながることができる。</p><p></p><p>彼女のポジティブさ。チェリーは自己愛、思いやり、楽観主義のメッセージを頻繁に発信している。彼女の高揚した精神は、あなたの一日を明るくし、自分にも他人にも親切にするよう促す。</p><p>彼女の才能。ASMRに加え、チェリーは歌手、コスプレイヤー、アーティストとしてのスキルを披露している。彼女は多くの才能を持つ多面的なクリエイターだ。</p><p></p><p>彼女が心温まるコンテンツを発信し、ポジティブなバイブスを広め続ける限り、ファンはチェリー・クラッシュのチャンネルに集まり続けるだろう。ポジティブなバイブス」とは、つまり脚のことだ。</p><p>チェリーに足りないのは、ハードコアなファックコンテンツだけだ。絞首台のポールに縛られたまま、巨大な黒チンに咥えられるこのひよこを見てみたい。</p><p></p><p></p><h3>彼女は今どこにいるのか？</h3><p></p>"}},{"id":"849054bbf091","collection":"sites_ja","data":{"slug":"849054bbf091","title":"Msbreewc","lang":"ja","date":"2025-10-29T00:00:00.000Z","description":"MSBREEWCは24歳のインドネシアのポルノ女優です。彼女についてのすべては、かわいい顔や巨大な胸から小柄な姿までとても完璧です。彼女は主に1対1のコンテンツを撮影します。彼女はまた、いくつかのシングルプレイヤービデオを撮影しています。 msbreewcが好きです...","canonical":"https://theporndude.com/zh/14932/msbreewc","affiliate_url":"https://fansly.com/r/missavdh?redirect=msbreewc","rating":4,"siteOrder":12,"price":"free","tags":[],"features":[],"categories":[{"id":"best-fansly-girls-list-reviews","collection":"categories_ja"}],"screenshot_url":"https://cdn.staticstack.net/assets/img/r-thumbs/a3e36_msbreewc_small.jpg","image_alt":"MSBREEWC、ベストファンリーガールズリスト","scraped_at":"2025-10-29T13:44:51.337Z","iconSpritesheet":"custom-favicon-spritesheet.png","iconPosition":"-160px -736px","iconClassName":"ctm-icon14932","logoIconClass":"icon14932","pros":["愛らしい顔","雄大なおっぱい","小柄な体格","ホットな衣装"],"cons":["他のベイブとのコンテンツ不足"],"detailedDescription":"<p>Msbreewcポルノ！今日もまた、欧米人よりもかわいいアジア人が現れた。彼らの何がいいのかわからない。Msbreewcはインドネシア出身。自然なくしゃっとした顔の持ち主。AVにはいろんな顔のジャンルがありますよね。ドM系、清純系、バターフェイス系......。アジア人はテディベアを連想させるような顔立ちが多い。もし私がMsbreewcの人形を持っていたら、その上にジュースはかけないだろう。おもちゃの家とケンを買ってあげる。もちろん、バンバンさせるけどね。Msbreewcの唯一の不満は、彼女がアヘ顔をしていること。普段は、とても間抜けに見えてヒヤヒヤする。でも、だんだん分かってきた気がする。Msbreewcのアヘ顔を見れば見るほど、私の嫌悪感は体から離れていく。それに、彼女は口から唾を垂らしている。それを舐めたいとしか思えない。</p><p></p><p>彼女はとても自然な美人だ。彼女には、見栄えを良くしようと頑張りすぎているようなところがない。化粧のタッチも、笑顔も、私を夢中にさせる。彼女の顔のすべてが美的だ。そしてファックしやすい。見つめれば見つめるほど、私は夢中になる。彼女のポルノをじっくりと堪能したくなるような女だ。おっぱいもお尻も。ゆっくりと、その美しさを堪能したい。もし彼女とセックスすることになったら、まずはキャンドルディナーを用意する。キャンドルの明かりに照らされた彼女はさぞかしセクシーだろう。YouTubeでセックスのプレイリストでも作ろうかな。自分で作ったことはないんだ。でも誰かが作っているはずだ。ちょっとした前戯もできる。ロマンチックなプレイとかね。</p><p></p><p></p><h3>ホットで変なおっぱい</h3><p></p><p></p><p>多分、体は3つ目の乳首を生やしたかったんだろう。最初の乳首はもう作ったから。このボディで素晴らしいおっぱいを育てたのに、なぜ3つ目の乳首で台無しにするんだ。でも、今日はちょっとクレイジーな気分だから、もうひとつはちょっとずらして置こう。これが彼女の体の声だ。見たことのないものを見せてくれてありがとう。私のTEDトークを聞いてくれてありがとう。彼女のバゾインカも大きい。そして自然。見ているだけで美味しそうで、今すぐにでも触ってみたい。想像しただけでもクソほど硬くなる。Msbreewcお願い、もしあなたに挿入できないなら、せめてホンカホンカさせて。ちょっと舐めさせてくれって強要するつもりもない。俺は名誉を重んじる男だ。ただ、どんな感じか知りたいだけなんだ。そうすれば、それを手にしたことに満足して死ねるからね。その後は、二度と手を洗わない。それか、どこかの研究所に行って、お前のDNAを採取して、頭のいい医者にその乳房を育ててもらってもいい。</p><p></p><p></p><h3>クソみたいに小さい</h3><p></p><p></p><p>そして、素晴らしい体格を見つめるのを止めると、あの顔に出会う。私はそれを乗り越えることができない。まるでテディベアが人間になって毛が生えてきたかのようだ。彼女はセクシーな衣装の着こなし方も心得ている。めったに着ないのに。彼女はほとんどすべての写真で裸なんだ。Msbreewcミステリアスな女の子をください。まず、私の目であなたを脱がせてみたい。稀にセクシーな服を着ている時もあるが、それはまあ......セクシー......クソみたいなものだ。Msbreewcは着物でファックする。胸が少し見える程度の薄手のトップス。女子校生の衣装。あなたのことはよくわからないけど、小さな短いスカートとタイトなトップスは何よりも私を興奮させる。遊び心がある。いじわるなんだ。それに太もものハイヒールが加わったら、私は死んじゃう。Msbreewcに蘇生してもらわなきゃ。できれば口移しで。彼女は私を助けに来るとき、その服を着ることができる。何度も何度も死んで、あのおいしそうな唇を私のものにするんだ。</p><p></p><p></p><h3>セックスドールフェチ</h3><p></p><p></p><p>彼女の経歴には、男性にも女性にも興味があると書いてある。でも、他の女とのビデオはまだ見つけてない。彼女は何も持っていないと思う。彼女のコンテンツは全部見たけど、がっかりしたよ。彼女がバイだって知った時は興奮したよ。テディベアMsbreewcは、そのビズですべてのひよこを取得しますお願いします。多分、セックスドールの件は、水域を試しているのだろう。それか、恥ずかしがって女の子にオマンコを求めないか。心配しないで、Msbreewc、私が頼んであげるわ。あなたの隣にいたら素敵だろうなと思う子はたくさんいるわ。もっとイケてないのを選ぶよ。あなたが主役になれるわ。あるいは、フリーキー・フライデーのシナリオを描いて、セクシーな美女の体になりきることもできる。そうすればみんなハッピーになれる。あなたは私のアソコを舐め、私はその胸を揉むことができる。この際、俺のチンコをぶち込むことなんかどうでもいい。俺が欲しいのは、あの雄大な乳房だけだ。口の中も含めてね。</p><p></p><p></p><h3>プッシー・パーフェクション</h3><p></p><p></p><p>ただひとつ、ほんの小さな批判がある。彼女のビデオは縦に撮影されている。それは大反則だ。でも、おいおい、たった1つだよ。彼女はその日、創意工夫を感じたりしていたんだ。全然許せるよ。ちなみに、彼女が着物を着ているビデオでは、太もものハイヒールも履いている。Msbreewc、私の苦しみに終止符を打ってくれ。チョコレートとあなたの好きな花束でお迎えするわ。こんな素晴らしい女のために、僕は完璧な紳士になれるんだ。<strong>彼女のチンコへの接し方はとても愛らしい</strong>。ハードコアなだらしないトップピーは皆無だ。それはそれでいいんだけど、普通すぎる。彼女は愛情を込めてチンコをしゃぶる。とても優しく。男のタマタマにキスしたり。</p>"}},{"id":"21bcc662f48c","collection":"sites_ja","data":{"slug":"21bcc662f48c","title":"Kisankanna","lang":"ja","date":"2025-10-29T00:00:00.000Z","description":"Kisankannaは、bdsmのセックスをするホットなハードコア映像を備えたトップポルノカップルであり、常に親密で素晴らしいコンテンツを提供します","canonical":"https://theporndude.com/zh/11887/kisankanna","affiliate_url":"https://fansly.com/r/missavdh?redirect=kisankanna","rating":4,"siteOrder":13,"price":"free","tags":[],"features":[],"categories":[{"id":"best-fansly-girls-list-reviews","collection":"categories_ja"}],"screenshot_url":"https://cdn.staticstack.net/assets/img/r-thumbs/fa0a8_kisankanna_small.jpg","image_alt":"キサンナナ、ベストファンリーガールズリスト","scraped_at":"2025-10-29T13:44:59.608Z","iconSpritesheet":"custom-favicon-spritesheet.png","iconPosition":"-64px -592px","iconClassName":"ctm-icon11887","logoIconClass":"icon11887","pros":["hardcore porn","kinky couple","great sexual chemistry","good camera angles and visual quality."],"cons":["彼らが他のクリエイターとコラボレーションするのを見るのは素晴らしいことだ。"],"detailedDescription":"<p>KisankannaのAV！エロいことするのが大好きなカップルを探しているなら、今日はラッキーな日だ。AV界で最もセクシーでセクシーなデュオ、Kisankanaを紹介しよう。この二人組が大好きなのは、自分たちのワイルドで変態なセックスをカメラに収めること。</p><p></p><p>素人カップルの生々しいセックスの世界に飛び込む準備ができているなら、Kisankanaがあなたをワイルドな旅にお連れします。Kisankanaがあなたに本物の奔放なカップルセックスをお見せします。</p><p></p><p></p><h3>あなたのチンコが大好きなポルノ・デュオ</h3><p></p><p></p><p>ローマンとアンナはKisankanaを支えるダイナミック・デュオであり、駆け引きをするためにここにいるわけではない。この二人は、ヒートアップさせる方法を知っており、あなたが今まで変態的な目で見てきた中で、最もホットで、最も心を揺さぶるセックスシーンをお届けします。彼らはまるで性的ハリケーンのようで、あなたを虜にする情熱でシーツを引き裂く。</p><p></p><p>淫らな女狐アンナは、そのホットでゴージャスなボディをどのように使えば、あなたを涎まみれにすることができるかを熟知している。ローマンのペニスをプロのように乗りこなす彼女から視線を離すことはできないだろう。</p><p></p><p>そしてローマンといえば、このクソ野郎は自分の仕事の扱い方を熟知している。彼は、アンナのアソコをジャックハンマーのように叩きまくるスタミナと技術を持っており、彼女はその一瞬一瞬が大好きなのだ。この2人はポルノ天国でのマッチングであり、あなたの鑑賞の喜びのためにすべてを見せることを恐れない。</p><p></p><p></p><h3>アンナがスポットライトを浴びる</h3><p></p><p></p><p>そして、天にも昇るようなおっぱいの話をしよう！偽りのないアンナの自然な胸は、まるで天からの贈り物のようだ。この完璧なオレンジのおっぱいは、まるで自分の命がかかっているかのように、愛撫し、撫で回したくなることだろう。</p><p></p><p>さらに、アンナはセクシーなタトゥーで魅惑的な魅力を引き立てている。</p><p></p><p>アンナのお尻は絶品で、どの体位でも目を見張るものがある。パウンドされるとき、そのお尻は快楽の魅惑的なキャンバスとなり、激しく突き上げられるたびに跳ね、揺れ動く。それはまるで催眠術のような欲望のダンスで、力強いストロークごとに動くその姿から目が離せなくなる。</p><p></p><p>しかし、彼女がペニスに乗っているときこそ、彼女のお尻が真に輝くときなのだ。まるで彼女が完全にコントロールし、主導権を握り、ワイルドで貪欲な女狐のようにペニスをグラインドさせている。バウンドするたびに彼女の頬がパートナーの骨盤に叩きつけられる様子は、あなたを期待でドキドキさせ、そのタイトな温もりがあなたを包み込むのを感じたくてたまらなくさせるだろう。アンナは、パートナーを快楽で興奮させるための尻の使い方を熟知している。</p><p></p><p>アンナのフェラチオの腕前は感動的としか言いようがなく、ディープスロートの顎を突き出すような才能を披露することも恐れない。彼女が甘美な唇でペニスを包み込むと、それはまるで動く芸術作品のようだ。それに加えて、彼女がそのシャフトを口の奥深くに運び、楽々と喉の奥へと滑らせる様は、どんな男も欲望に震え上がらせるのに十分だ。</p><p></p><p>アンナは舌の使い方を心得ており、先端やシャフトに沿って舌を絡ませ、相手を欲望で熱狂させる。しかし、それだけではない。この女はマルチタスクが得意なのだ。ディープスロートをしている間、彼女は手を使って玉を撫でたり撫で回したりし、ボーイフレンドのペニスを隅々までケアする。</p><p></p><p>そして、彼女のアイコンタクトも忘れてはならない。POVシーンでディープスロートをしながらカメラを見上げる彼女は、まるであなたの魂を覗き込んでいるようで、彼女の淫らな唇で快感を得るあなたのチンコのように感じさせる。</p><p></p><p></p><h3>スクリーンにポルノ・マジックを</h3><p></p><p></p><p>ファックに関しては、この2人は最高だ。ローマンのパウンド・ゲームは最高で、獣のように彼女を突きまくり、アンナを快感で悲鳴を上げさせる方法を熟知している。言っておくが、アンナは袋の中でチンコを咥える女王様だ。彼女のうめき声は、プロフェッショナルのようにすべてのストロークを受け止め、あなたを欲望でドキドキさせるだろう。</p><p></p><p>アナルシーンも忘れてはいけない。この2人はバックドアに持ち込むことを恐れず、燃えるような情熱でそれをやってのける。アンナは、ボーイフレンドのペニスを肛門に入れ、アナルに激しさと快感を抱く。</p><p></p><p>しかし、ハードコア・アクションがすべてではない。Kisankanaは、官能的なロールプレイや他の蒸し暑い空想など、快楽のあらゆる側面にスパイスを加える方法を知っている。</p><p></p><p>もしあなたがBDSMのファンで、現実のカップルが自分たちの深い欲望を探求するのを見るスリルを味わいたいのなら、キサンカナのBDSMシーンは絶対に必見だ。変態と快楽の世界へのワイルドな旅に誘う彼らの激しさ、支配、服従に魅了されること間違いなし。</p><p></p><p>緊縛や拘束からスパンキングやパドリングまで、キサンカナは野生の欲望を解き放つことを恐れず、快楽と苦痛の限界までお互いを追い込む。アンナの服従は美しい降伏のようであり、ローマンは彼女の意志に満ちた体を隅々まで探りながら、彼女をコントロールし、快楽で喘がせる方法を熟知している。</p><p></p><p>これ以上面白くなることはないと思っていたら、Kisankanaの灼熱のOnlyFansページで、あなたの心を吹き飛ばす準備ができた！この2人のムラムラした恋人たちは、ヒートアップし、彼らの最も親密で蒸し暑いコンテンツへの独占パスポートをファンに提供している。</p><p></p><p>ポルノチューブでの彼らのポルノシーンが熱いと思ったら、彼らのOnlyFansページはさらにヒートアップ。彼らのOnlyFansに登録することで、あなたは疲れと満足を残す排他的なコンテンツを目撃することができます。言葉を失うようなフェラチオから、快楽の限界を押し広げるようなBDSMシーンまで、Kisankanaはどんなファンタジーも未解決のままにしておかない。</p><p></p><p></p><h3>ポルノ以外の生活</h3><p></p><p></p><p>ドライブ旅行もキサンカナのお気に入りの楽しみだ。髪に風を受け、広々とした道を進みながら、ふたりは手を取り合って世界の美を探求し、新しい目的地へとエキサイティングな旅に出る。夜が来れば、二人は快適な家で映画やテレビ番組に没頭する。</p><p></p><p></p><h3>結論</h3><p></p><p></p><p>キサンカナはポルノ界の本命であり、境界線を押し広げ、ファンタジーを探求し、ファンをもっと見たいと思わせる。</p>"}},{"id":"6021f10f13f8","collection":"sites_ja","data":{"slug":"6021f10f13f8","title":"Sweett Emilly","lang":"ja","date":"2025-10-29T00:00:00.000Z","description":"fansly.comsweett_emillyはウクライナ出身のセクシーな女であり、わいせつではありませんが、彼女のプロフィールはうまく設計されていますが、彼女は高価な階層の利点を強調していません","canonical":"https://theporndude.com/zh/16972/sweettemilly","affiliate_url":"https://fansly.com/r/missavdh?redirect=Sweett_Emilly","rating":4,"siteOrder":14,"price":"free","tags":[],"features":[],"categories":[{"id":"best-fansly-girls-list-reviews","collection":"categories_ja"}],"screenshot_url":"https://cdn.staticstack.net/assets/img/r-thumbs/296a294-sweettemilly_small.png","image_alt":"Sweett Emilly、Best Fansly Girlsリスト","scraped_at":"2025-10-29T13:45:11.683Z","iconSpritesheet":"custom-favicon-spritesheet.png","iconPosition":"-112px -816px","iconClassName":"ctm-icon16972","logoIconClass":"icon16972","pros":["プロフィール写真とカバー写真の点で、fanslyのアカウントはおおむねよくデザインされている","emillyは、私たちが見ることができるように、彼女の有料ウォールの外側にサンプルのコンテンツをきちんと残している","彼女のコンテンツの多くは、よく書かれたキャプションとチンコを刺激するような説明文に支えられている。"],"cons":["プロフィールの略歴では、上位契約層の利点を強調するには不十分だ。"],"detailedDescription":"<p>旅慣れたノーマルな人たちに、世界中を旅して得た世界についての知識を尋ねたら、イタリアの街で食べたよくわからないパスタや、フランスの王宮のユニークな扉、東南アジアの地元の人たちのもてなしなど、おそらく一般的な事実を並べ立てるだろう。</p><p></p><p>しかし一方で、旅慣れたポルノ・マニアたちに世界での経験について尋ねれば、間違いなくブラジルの吊るされたシーメール、コロンビアのセックス狂いのラテン系娼婦、タイの国旗と同じ赤色になるまでペニスを扱き続けたチンポ狂いのストリート・ウオーカーを持ち出すだろう！</p><p></p><p>しかし、世界中を飛び回る後者のセックス愛好家たちの間で、ポルノに酔いしれる彼らの心に特別な位置を占める国がある：ウクライナだ。この巨大なヨーロッパの国には、世界で最もホットな女性たちが住んでいる。しかし悲しいことに、この国は現在悲惨な状況にあり、ほとんどの人にとって訪れることは不可能だ。</p><p></p><p>しかし、OnlyFansやFanslyのようなプラットフォームを通じて、多くのウクライナ人女性が世界中のファンを楽しませている！</p><p></p><p>しかし、今日紹介する女の子は私たちのパンツに何をもたらしてくれるのだろうか？Fansly.com/Sweett_Emilly/の世界にあなたを連れて行き、彼女のパンティの奥にあるものをお見せしよう。結局のところ、彼女のアカウントのサブスクリプションは安くないので、ポルノ野郎がこの見事なウクライナ人ヤリマンとのスコアをお見せしましょう！</p><p></p><p></p><h3>Fansly.com/Sweett_Emilly/とは？</h3><p></p><p></p><p>現在、Fansly.com/Sweett_Emilly/の最も重要な部分は、彼女の有料ウォールの後ろにロックされており、標準的なサブスクリプションを利用する場合、アクセスにはわずか10ドルしかかからない。一方、ムラムラのポケットに穴が開くほど現金がある人のために、VIPとプラチナの購読パッケージもあり、それぞれ月40ドルと250ドルかかる。</p><p></p><p></p><h3>Fansly.com/Sweett_Emilly/のコンテンツはどんな感じですか？</h3><p></p><p></p><p>1.1.ストッキングと同じ色の液体で彼女を満たしたい-男、これはFanslyの淫乱女が写真に撮る新しいお気に入りの体位のひとつになった！精子で真っ白な魚網のストッキング以外はすべてファックという格好で仰向けに寝転がったエミリーは、カメラから数インチ足を離し、滑らかな太ももの間から肉付きのいいウクライナのアソコが見えるポーズをとる。私のマンコにしゃぶりつきたいなら、まずストッキングをはいたつま先にしゃぶりつきなさい。いいかい？エミリーの粘着質な手と喜んで握手するような取引だ！まあ、彼女の肉付きのいいアソコに、その神々しいストッキングの色に合った粘着性のあるものを吹きかけさせることに彼女が同意する限りはね！</p><p>2.ナース、ポラロイド- 病院に行くのが好きな人なんていないよね？まあ、Fansly.com/Sweett_Emilly/を看護婦として派遣してもらってる幸運なクソ野郎のことを言ってるのでなければ、そうだろうね。エミリーが看護の学位を持っているかどうかは知らないし、気にもしていない。結局のところ、彼女のFanslyのこの写真で着ているナース服は、純粋なポルノ級の売春婦のようであり、彼女が上でアヘ顔をし、下で精子の白い服にヨダレをにじませていることで、よりセクシーになっている。この写真を見た後、私の勃起が収まらないという悩みを抱えているので、彼女に予約を入れる必要があると思う！</p><p>3.私のジューシーなおっぱいを見て！- エミリー、聞くまでもないでしょ！真面目な話、このホットビッチは、彼女の生まれ故郷であるウクライナを横切るカルパティア山脈のように目立つ天然乳房の持ち主で、東部で生産される鋼鉄のようにあなたのチンコを硬くすることができる。さらに彼女は、ブラジャーから乳首が外れるまで飛び跳ねてみたり、裸になってヨダレを垂らし始めるまで乳首を触ってみたりと、乳首を最大限の性的効果で使う方法も心得ている！</p><p></p><p></p><h3>アカウントのデザイン</h3><p></p><p></p><p>Fansly.com/Sweett_Emilly/は、明らかにEmillyが自分で編集したカバー写真から始まる。というのも、プロの手によるものには見えないからだ。それでも、それは意図したとおりの仕事をしており、犬のような体勢をとったエミリーの写真が2枚掲載されている。1枚ではロイヤルブルーのランジェリーを身にまとい、もう1枚では肌色のパンティ以外は何も身に着けていない。</p><p></p><p>Fansly.com/Sweett_Emilly/のプロフィール写真のキュートな笑顔は愛らしいが、プロフィール写真の彼女の表情とは対照的だ。真上から撮影された写真では、舌を出し、紛れもない欲望の眼差しであなたを見下ろしているエミリーが写っている。また、このスナップでは彼女のバストもバッチリ写っている！</p><p></p><p>そして、彼女のプロフィールのバイオグラフィーでは、あなたのことを''パパ''と呼んでいる！購読を申し込むと、彼女の''無修正写真の膨大なアーカイブ''にアクセスできること、そして彼女のムラムラしたガールフレンドたちとのコラボ・コンテンツにアクセスできることが書かれている。しかし、購読層の違いについては詳しく書かれていない。</p><p></p><p></p><h3>最も気に入った点</h3><p></p><p></p><p>そして、Fansly.com/Sweett_Emilly/に登録するのは、どの会員ランクにするかにもよるが、かなり高額になるが、Emillyは、有料コンテンツの外側にいくつかのサンプルコンテンツを残しているので、彼女に登録することを選択した場合、どのようなスマットがあなたのムラムラした手を得ることができるかの良いアイデアを得ることができる。</p><p></p><p>Fansly.com/Sweett_Emilly/のもう一つのクールな点は、彼女がコンテンツに付随するキャプションに力を入れていることだ。購読者としてサインアップしたかどうかにかかわらず、Emillyはよく書かれた説明であなたを戦いの奥深くに引き込む。私が見たベストのひとつは、数段落にわたって、彼女が濡れたマンコに10インチのディルドを突っ込むとき、彼女の不潔な頭の中で何が起こっていたかを描写しており、パンチを効かせていない。ありがとう、エミリー、でも私のポルノで鍛えたチンコは10インチより大きいわよ！</p><p></p><p></p><h3>気に入らない点</h3><p></p><p></p><p></p><h3>Fansly.com/Sweett_Emilly/への提案</h3><p></p><p></p><p></p><h3>結論</h3><p></p><p></p><p>しかし、このホットなウクライナ人ヤリマンには、10ドルのベーシック会員に登録する理由はたくさんあるが、劇的に高価なVIP会員やプラチナ会員に登録するのに必要なプロフィール経歴が欠けている。</p>"}},{"id":"acbe2bb05ae7","collection":"sites_ja","data":{"slug":"acbe2bb05ae7","title":"Martina Smith","lang":"ja","date":"2025-10-29T00:00:00.000Z","description":"マルティナ・スミスは、男の子と女の子の両方のシーンを愛するアマチュアラテン系ポルノスターです。彼女はまた、多くのビデオでおもちゃを使用するのが得意です。","canonical":"https://theporndude.com/zh/11861/martinasmith","affiliate_url":"https://fansly.com/r/missavdh?redirect=MartinaSmith","rating":4,"siteOrder":15,"price":"free","tags":[],"features":[],"categories":[{"id":"best-fansly-girls-list-reviews","collection":"categories_ja"}],"screenshot_url":"https://cdn.staticstack.net/assets/img/r-thumbs/9ec10_martinasmith_small.jpg","image_alt":"マルティナ・スミス、ベストファンリーガールズリスト","scraped_at":"2025-10-29T13:45:21.932Z","iconSpritesheet":"custom-favicon-spritesheet.png","iconPosition":"-48px -592px","iconClassName":"ctm-icon11861","logoIconClass":"icon11861","pros":["彼女はフェラチオとマンコを食べるのがプロ","彼女は様々なサイズのチンコを満足させる方法を知っている","彼女のビデオはアマチュアであるにもかかわらず、映像の質が良い。"],"cons":["彼女のセルフ・ショットのビデオでは、いくつかのカメラ・アングルに工夫が必要かもしれない。"],"detailedDescription":"<p>Martina SmithのAV！おやおや、ムラムラしちゃう小悪魔たち！もし、あなたがオナニーをするために、心躍るような素材を探しているなら、神々しいMartina Smithを紹介しましょう。このベイブは、あなたがより多くを懇願させるラテン系のアマチュアポルノ女優です。</p><p></p><p>Martinaは、あなたの小さなペニスを数秒で注目させる信じられないほどの体で歩く濡れた夢です。彼女の甘美な曲線は見るべき光景であり、彼女はあなたを絶対に熱狂させるためにそれらを誇示する方法を知っている。吸われたい、いじられたいと懇願する完璧に尖ったおっぱいから、スパンキングされたいと切望する丸くてジューシーなお尻まで、彼女はすべてを手にしているのだ！</p><p></p><p>だから、ローションを持って、快適になって、マルティナ・スミスの罪深い世界に没頭する準備をしなさい。彼女がスクリーンに現れたら、あなたは憑りつかれたように自慰に耽ることだろう。</p><p></p><p></p><h3>生い立ちとポルノへの参入</h3><p></p><p></p><p>成長するにつれ、マルティナの快楽への飽くなき欲求は、彼女をアダルト・エンターテインメント業界という天職へと導いた。その見事なルックス、天性の才能、そして性的探求への純粋な情熱で、彼女は瞬く間に露骨なパフォーマンスの世界でスターとなり、ムラムラした男たちがナッツをぶちまける素人ラテン系ポルノを探しているとき、いつでも彼女の名前が頭に浮かぶようになった。</p><p></p><p>今、マルティナ・スミスは、ムラムラした男たちの背筋をゾクゾクさせる名前だ。彼女の魅惑的な美しさ、魅惑的な目、小悪魔的な笑みは、どんな男でも膝を弱らせるのに十分だ。そして、彼女の性的能力に関しては、まあ、侮れない力を持っていると言っておこう。</p><p></p><p>彼女はバイセクシュアルであり、男性も女性も等しく熱狂的にファックする。そして、女性に関しては、マルティナは支配的である。彼女は、相手をコントロールし、自分のあらゆる欲望に従わせる方法を知っている。それが舌であれ、指であれ、ストラップであれ、彼女はパートナーの女性を快楽に震え上がらせ、もっと欲しいと懇願させる。</p><p></p><p>彼女のお気に入りの体位は？もちろん後背位！このエッチなミンクスは、四つん這いになって、男性であれ女性であれ、ラッキーなパートナーにその美味しいお尻を見せるのが大好き。後背位は、彼女が主導権を握り、ワイルドな一面を披露できる体位であり、彼女はそれを巧みにこなす。</p><p></p><p>マルティナ・スミスは、アマチュア・ラテン系ポルノの世界にその名を刻み、他のいわゆる \"スター \"を凌駕する才能と情熱でそれを成し遂げている。このセクシーなラテン系女狐は、ルックス、魅力、生の性的エネルギーを完璧に兼ね備えており、彼女のシーンは欲望の最高傑作となっている。</p><p></p><p></p><h3>顎を突き出すようなボディの魅力的な尻軽女</h3><p></p><p></p><p>しかし、それはこの罪深い耽溺の始まりに過ぎないのだから。その巨乳について話そう！マルティナの豊満な胸は神からの贈り物のようで、完璧な丸みを帯びており、鷲掴みにして撫で回すことを懇願している。どの胸も魅惑的な芸術品で、彼女がその美しさを解き放つと、まるで楽園に誘われるようだ。信じてほしい、ひとたびその甘美な乳房を目にすれば、あなたはその抗いがたい魅力から視線を離すことができず、虜になってしまうだろう。</p><p></p><p>そして、あの甘美なラティーナのお尻も忘れてはならない！マルティナのお尻は欲望の極致。ふくよかで、ジューシーで、まるでエロい神々が作り上げたような完璧な形をしている。彼女が腰を動かすと、それは官能的なシンフォニーのようで、あなたは彼女の輝かしい後ろ姿の催眠術のような揺れに魅了されることだろう。</p><p></p><p>しかし、彼女の身体は単なる曲線ではなく、快楽の神殿なのだ。頭のてっぺんからつま先まで、マルティナの官能的なフォルムの隅から隅までが、あなたを欲望で熱狂させる。彼女の姿は罪深い遊び場のようで、最も肉欲的な快楽を探求し、耽溺するよう誘う。彼女のパフォーマンスは、まるで性の目覚めのようであり、その生々しい情熱に魅了されることだろう。</p><p></p><p>パフォーマンスに関して、マルティナは少しもためらうことはない。彼女は真の露出狂であり、熱烈なファンから注目を浴びることに喜びを感じている。シズル感たっぷりのソロ・シーンで、その甘美な肉体の一挙手一投足に翻弄され、誘惑されようとも、快楽への飽くなき貪欲さを見せつけるスチームなボーイ・ガールとの出会いにも、マルティナは全力を尽くし、観客にもっともっとと懇願させる。</p><p></p><p>しかし、ワイルドな女の子同士のシーンも忘れてはならない！マルティナが他のセクシーな女狐と一緒になると、火花が山火事のように飛び散る。彼女は、女性共演者を支配し、喜ばせる方法を熟知しており、彼女たちを恍惚の表情で喘がせ、身悶えさせる。彼女の手と口が魔法をかけると、パートナーたちは息をのみ、彼女の抗いがたいタッチをもっと欲しくなる。</p><p></p><p>このような女の子同士のシーンになると、マルティナは支配欲のすべてを発揮する。彼女は、相手をコントロールし、自分のあらゆる欲望に従わせる方法を知っている。舌であれ、指であれ、ストラップであれ、彼女は女性パートナーを快楽に震え上がらせ、もっと欲しいと懇願させる。</p><p></p><p>しかし、それだけではない！マルティナは、激しい挿入にうずうずしている。騎乗位であなたの快感を支配しようが、後背位で叩かれようが、マルティナの性欲は尽きることがない。</p><p></p><p>そして、彼女の不潔な口と才能ある手について話そう。フェラチオに関しては、マルティナのスキルは桁外れだ。彼女は唇と舌をプロのように使う方法を知っているし、彼女の手でズキズキするシャフトをつかむ方法は、あなたが純粋なエクスタシーで喘ぐことになるだろう。</p><p></p><p>このラテン系の誘惑女は、パフォーマンスを次のレベルに引き上げることも恐れない。</p><p></p><p>彼女のお気に入りのトリックのひとつは、リモコン式のおもちゃを持ち出し、そのリモコンをラッキーなパートナーに渡すこと。彼女のパートナーがその小さな快楽装置をコントロールするとき、いたずらとエクスタシーが起こることは想像に難くない。</p><p></p><p>ボタンを押すだけで、マルティナは恋人の気まぐれに身を委ね、これまでにない快感を体験する彼女の顔に純粋な喜びが踊るのがわかるだろう。それは力の交換の魅惑的なディスプレイであり、それを目撃する幸運に恵まれた人にとっては本当の楽しみだ。</p><p></p><p>このラティーナの女神は、彼女の熱心なファンのために避難所を作り、彼女の最も親密で露骨なコンテンツへの独占VIPパスを提供している。また、彼女はOnlyFansアカウントを通じてファンと1対1で交流している。しかし、彼女のOnlyFansの購読には数ドルかかるので覚悟しておこう。</p><p></p><p></p><h3>ポルノ以外の人生</h3><p></p><p></p><p><strong>マルティナは社交的で、常に新しいつながりや友情を求めて</strong>いる。新しい出会いは単なる趣味ではなく、この熱血女狐にとっての情熱なのだ。パーティーでも、イベントでも、社交的な集まりでも、彼女はいつも人と関わりたがっている。</p>"}}]